Workbook

Sheet Instruction Sheet
A8: Please change the Date & Currency settings of your systems for easy usage of this tool( First time only)
A9: Step 1 : Double click on Control Panel Step 2 :Select small icons in View By options(Right top Side ) - Step 3 :Select Region and Language icon Step 4 : In Format tab select "English(India)" option Step 5 :Click on Additional settings- 1. Date Settings: Select Date tab- Select Short date format as "dd-MM-yyyy" 2.Currency Settings: Select Currency tab- In Currency Symbol select "Rs." options - Click Ok
A19: Master Maintenance
A20: Office Name | C20: Strategic Alliance Auto Tieup Hub (Patna)
A21: Short Office Name | C21: SAATH, Patna
A22: Incharge Designation | C22: Incharge
A23: Address | C23: "Jeewan Prakash", Fraser Road
A24: City | C24: Patna | J24: Developed by:
A25: State | C25: Bihar | J25: 1. Ritesh K Sinha | L25: SAATH, Patna | N25: 8405802622
A26: Pin Code | C26: 800001 | J26: 2. Rajiv Ranjan | L26: PTRO | N26: 8405802652
J27: 3.Ranjeet Kumar SAATH, Patna 8409473204
A28: Release Version 4.3 Dt. 29/11/2022 | K28: (For Internal Use only)

Sheet Checlikst
A1: Checklist
A2: ='Data Entry'!B45 -> Aastha Honda Patna
A3: Claim Details
A4: Claim No. | B4: ='Data Entry'!B3 -> 0 | E4: Checked By:
A5: Policy No. | B5: ='Data Entry'!B4 -> 0
A6: Insured Name | B6: ='Data Entry'!B5 -> Mr.
A7: Expiry Date | B7: ='Data Entry'!D10 -> 0
A8: Reg. No. | B8: ='Data Entry'!B18 -> 0
A9: Model | B9: ='Data Entry'!B23 -> M/S Maruti
A10: Date of Accident | B10: ='Data Entry'!B38 -> 0
A12: Document Submitted
B13: DL Copy | E13: FIR Copy
B14: Policy Copy | E14: Reg. Copy
B15: Claim Form Duly Filled
B16: 64 VB | E16: NCB Certificate
B17: Invoice | E17: Estimate
B18: Photographs | E18: Satisfaction Voucher
B19: Pre-Inspection Report
A21: Surveyor Detail
A22: Spot Survey | B22: =IF('Processing Sheet'!C9<>"",'Processing Sheet'!C9,"") | C22: Survey Date | E22: =IF('Processing Sheet'!C10<>"",'Processing Sheet'!C10,"")
A23: Final Survey | B23: =IF('Processing Sheet'!F9<>"",'Processing Sheet'!F9,"") -> Dilip Kumar Sinha | C23: Survey Date | E23: =IF('Processing Sheet'!F10<>"",'Processing Sheet'!F10,"")
A24: Reinspection Survey | B24: =IF('Processing Sheet'!I9<>"",'Processing Sheet'!I9,"") | C24: Survey Date | E24: =IF('Processing Sheet'!I10<>"",'Processing Sheet'!I10,"")
A26: Assessment
A27: NIC Invoice Amount
A28: Customer Invoice Amt
A29: Money Receipt | B29: =IF('Processing Sheet'!D59<>"",'Processing Sheet'!D59,"")
A30: Assessment | B30: ='Processing Sheet'!H59 -> -1000
A31: Difference | F31: Ver 4.3
A33: ------------------------------------- Please tear from here ----------------------------------------------
A35: AKNOWLEDGEMENT
A36: ="We, hereby acknoledge the receipt of the following claim file to be submitted to National Insurance Co. Ltd, "&'Instruction Sheet'!C20 -> We, hereby acknoledge the receipt of the following claim file to be submitted to National Insurance Co. Ltd, Strategic Alliance Auto Tieup Hub (Patna)
A37: Claim No. | B37: =B4 -> 0
A38: Policy No. | B38: =B5 -> 0
A39: Insured Name | B39: =B6 -> Mr.
A40: Reg. No. | B40: =B8 -> 0
A41: Model | B41: =B9 -> M/S Maruti
A42: Date of Accident | B42: =B10 -> 0
A43: Survey Date | B43: =E23
A44: Surveyor | B44: =B23&" (SLA : "&'Data Entry'!B66&")" -> Dilip Kumar Sinha (SLA : 63315)
A46: Date :
F47: (Authorised Signatory)
F48: =A2 -> Aastha Honda Patna

Sheet Delivery Order
A3: NATIONAL INSURANCE COMPANY LIMITED
A4: ='Instruction Sheet'!C20&", "&'Instruction Sheet'!C23&", "&'Instruction Sheet'!C24&"-"&'Instruction Sheet'!C26&", "&'Instruction Sheet'!C25 -> Strategic Alliance Auto Tieup Hub (Patna), "Jeewan Prakash", Fraser Road, Patna-800001, Bihar
A6: DO / Liability Letter
F7: Date : | G7: ='Processing Sheet'!I12 -> 46137
A9: To,
A10: ='Data Entry'!B45 -> Aastha Honda Patna
A11: ='Data Entry'!H6 -> Patna
A13: ="Surveyor : "&'Data Entry'!B60 -> Surveyor : Dilip Kumar Sinha | F13: Date of Accident : | G13: ='Data Entry'!B38 -> 0
A14: ="Insured Name : " &'Data Entry'!B5 -> Insured Name : Mr.
A15: ="Vehicle Reg No : "&'Data Entry'!B18&" Chasis No. : "&'Data Entry'!B21&" Vehicle Model : "&'Data Entry'!B23 -> Vehicle Reg No : Chasis No. : Vehicle Model : M/S Maruti
A16: ="Claim No : "&'Data Entry'!B3 -> Claim No :
A17: ="Policy No. : " & 'Data Entry'!B4 -> Policy No. :
A19: With reference to the above claim details, our liability towards the above Claim as below. Request you to deliver the vehicle by collecting difference amount.
A21: ="Invocie No. : " & 'Processing Sheet'!D61 -> Invocie No. : JC25001035 | E21: Dated : | F21: ='Processing Sheet'!I61 -> 45977
A22: ="Invoice amount : Rs."&'Processing Sheet'!D60&"/-" -> Invoice amount : Rs.23047/-
A23: ="Claim Liability : Rs."&MIN('Processing Sheet'!H58,('Processing Sheet'!D60-'Processing Sheet'!D59))&"/-" -> Claim Liability : Rs.-1000/-
A25: We shall release the payment within 7 working days (if claim amount is <1.50 Lakh)/ 14 working days (if claim amount >1.5 LAKH) from the date of receipt of last relative document and money receipt.
A28: Thanks & Regards
A29: National Insurance Co Ltd
A30: SAATH, Patna
B37: Phone No. 0612-2200280/2200407 Website: www.nationalinsuranceindia.com
A42: Replacement of Parts : | D42: ="Depreciation on Metal Parts : "&'Processing Sheet'!E31&"%" -> Depreciation on Metal Parts : 0%
A43: SL NO | B43: NAME OF PARTS | C43: MATERIAL OF PARTS | D43: GST | E43: Insurance Co.'s Liability | F43: GST | G43: Insured's Liability | H43: GST
A44: 1 | B44: Cost of Paint Material (25% of Lumpsum Painting Labour Charge) | C44: PAINT (Labour) | D44: =IF('Assessment Sheet'!D79<>"",'Assessment Sheet'!D79,"") -> 0.18 | E44: =IF('Assessment Sheet'!I79<>"",'Assessment Sheet'!I79,"") -> 0 | F44: =IF('Assessment Sheet'!J79<>"",'Assessment Sheet'!J79,"") -> 0 | G44: =IF(E44<>"",('Processing Sheet'!#REF!-'Processing Sheet'!#REF!),"") -> #REF! | H44: =IF(G44<>"",G44*D44/100,"") -> #REF!
A45: 2 | B45: Cost of Paint Material (Calculated on a segregated basis Parts) | C45: PAINT | D45: =IF('Assessment Sheet'!D80<>"",'Assessment Sheet'!D80,"") -> 0.18 | E45: =IF('Assessment Sheet'!I80<>"",'Assessment Sheet'!I80,"") -> 0 | F45: =IF('Assessment Sheet'!J80<>"",'Assessment Sheet'!J80,"") -> 0 | G45: =IF('Processing Sheet'!#REF!=0,0,IF(E45<>"",('Processing Sheet'!#REF!-'Processing Sheet'!#REF!),"")) -> #REF! | H45: =IF(G45<>"",G45*D45/100,"") -> #REF!
A47: 1 | B47: =IF('Assessment Sheet'!B81<>"",'Assessment Sheet'!B81,"") | C47: =IF('Assessment Sheet'!C81<>"",'Assessment Sheet'!C81,"") -> PLASTIC | D47: =IF('Assessment Sheet'!C81<>"",'Assessment Sheet'!D81,"") -> 0.18 | E47: =IF('Assessment Sheet'!B81<>"",'Assessment Sheet'!I81,"") | F47: =IF('Assessment Sheet'!J81<>"",'Assessment Sheet'!J81,"") -> 0 | G47: =IF(E47<>"",('Processing Sheet'!#REF!-'Processing Sheet'!#REF!),"") | H47: =IF(G47<>"",G47*D47/100,"")
A48: 2 | B48: =IF('Assessment Sheet'!B82<>"",'Assessment Sheet'!B82,"") | C48: =IF('Assessment Sheet'!C82<>"",'Assessment Sheet'!C82,"") -> PLASTIC | D48: =IF('Assessment Sheet'!C82<>"",'Assessment Sheet'!D82,"") -> 0.18 | E48: =IF('Assessment Sheet'!B82<>"",'Assessment Sheet'!I82,"") | F48: =IF('Assessment Sheet'!J82<>"",'Assessment Sheet'!J82,"") -> 0 | G48: =IF(E48<>"",('Processing Sheet'!#REF!-'Processing Sheet'!#REF!),"") | H48: =IF(G48<>"",G48*D48/100,"")
A49: 3 | B49: =IF('Assessment Sheet'!B83<>"",'Assessment Sheet'!B83,"") | C49: =IF('Assessment Sheet'!C83<>"",'Assessment Sheet'!C83,"") -> PLASTIC | D49: =IF('Assessment Sheet'!C83<>"",'Assessment Sheet'!D83,"") -> 0.18 | E49: =IF('Assessment Sheet'!B83<>"",'Assessment Sheet'!I83,"") | F49: =IF('Assessment Sheet'!J83<>"",'Assessment Sheet'!J83,"") -> 0 | G49: =IF(E49<>"",('Processing Sheet'!#REF!-'Processing Sheet'!#REF!),"") | H49: =IF(G49<>"",G49*D49/100,"")
A50: 4 | B50: =IF('Assessment Sheet'!B84<>"",'Assessment Sheet'!B84,"") | C50: =IF('Assessment Sheet'!C84<>"",'Assessment Sheet'!C84,"") -> PLASTIC | D50: =IF('Assessment Sheet'!C84<>"",'Assessment Sheet'!D84,"") -> 0.18 | E50: =IF('Assessment Sheet'!B84<>"",'Assessment Sheet'!I84,"") | F50: =IF('Assessment Sheet'!J84<>"",'Assessment Sheet'!J84,"") -> 0 | G50: =IF(E50<>"",('Processing Sheet'!#REF!-'Processing Sheet'!#REF!),"") | H50: =IF(G50<>"",G50*D50/100,"")
A51: 5 | B51: =IF('Assessment Sheet'!B85<>"",'Assessment Sheet'!B85,"") | C51: =IF('Assessment Sheet'!C85<>"",'Assessment Sheet'!C85,"") -> GLASS | D51: =IF('Assessment Sheet'!C85<>"",'Assessment Sheet'!D85,"") -> 0.18 | E51: =IF('Assessment Sheet'!B85<>"",'Assessment Sheet'!I85,"") | F51: =IF('Assessment Sheet'!J85<>"",'Assessment Sheet'!J85,"") -> 0 | G51: =IF(E51<>"",('Processing Sheet'!#REF!-'Processing Sheet'!#REF!),"") | H51: =IF(G51<>"",G51*D51/100,"")
A52: 6 | B52: =IF('Assessment Sheet'!B86<>"",'Assessment Sheet'!B86,"") | C52: =IF('Assessment Sheet'!C86<>"",'Assessment Sheet'!C86,"") -> PLASTIC | D52: =IF('Assessment Sheet'!C86<>"",'Assessment Sheet'!D86,"") -> 0.18 | E52: =IF('Assessment Sheet'!B86<>"",'Assessment Sheet'!I86,"") | F52: =IF('Assessment Sheet'!J86<>"",'Assessment Sheet'!J86,"") -> 0 | G52: =IF(E52<>"",('Processing Sheet'!#REF!-'Processing Sheet'!#REF!),"") | H52: =IF(G52<>"",G52*D52/100,"")
A53: 7 | B53: =IF('Assessment Sheet'!B87<>"",'Assessment Sheet'!B87,"") | C53: =IF('Assessment Sheet'!C87<>"",'Assessment Sheet'!C87,"") | D53: =IF('Assessment Sheet'!C87<>"",'Assessment Sheet'!D87,"") | E53: =IF('Assessment Sheet'!B87<>"",'Assessment Sheet'!I87,"") | F53: =IF('Assessment Sheet'!J87<>"",'Assessment Sheet'!J87,"") -> 0 | G53: =IF(E53<>"",('Processing Sheet'!#REF!-'Processing Sheet'!#REF!),"") | H53: =IF(G53<>"",G53*D53/100,"")
A54: 8 | B54: =IF('Assessment Sheet'!B88<>"",'Assessment Sheet'!B88,"") | C54: =IF('Assessment Sheet'!C88<>"",'Assessment Sheet'!C88,"") | D54: =IF('Assessment Sheet'!C88<>"",'Assessment Sheet'!D88,"") | E54: =IF('Assessment Sheet'!B88<>"",'Assessment Sheet'!I88,"") | F54: =IF('Assessment Sheet'!J88<>"",'Assessment Sheet'!J88,"") -> 0 | G54: =IF(E54<>"",('Processing Sheet'!#REF!-'Processing Sheet'!#REF!),"") | H54: =IF(G54<>"",G54*D54/100,"")
A55: 9 | B55: =IF('Assessment Sheet'!B89<>"",'Assessment Sheet'!B89,"") | C55: =IF('Assessment Sheet'!C89<>"",'Assessment Sheet'!C89,"") | D55: =IF('Assessment Sheet'!C89<>"",'Assessment Sheet'!D89,"") | E55: =IF('Assessment Sheet'!B89<>"",'Assessment Sheet'!I89,"") | F55: =IF('Assessment Sheet'!J89<>"",'Assessment Sheet'!J89,"") -> 0 | G55: =IF(E55<>"",('Processing Sheet'!#REF!-'Processing Sheet'!#REF!),"") | H55: =IF(G55<>"",G55*D55/100,"")
A56: 10 | B56: =IF('Assessment Sheet'!B90<>"",'Assessment Sheet'!B90,"") | C56: =IF('Assessment Sheet'!C90<>"",'Assessment Sheet'!C90,"") | D56: =IF('Assessment Sheet'!C90<>"",'Assessment Sheet'!D90,"") | E56: =IF('Assessment Sheet'!B90<>"",'Assessment Sheet'!I90,"") | F56: =IF('Assessment Sheet'!J90<>"",'Assessment Sheet'!J90,"") -> 0 | G56: =IF(E56<>"",('Processing Sheet'!#REF!-'Processing Sheet'!#REF!),"") | H56: =IF(G56<>"",G56*D56/100,"")
A57: 11 | B57: =IF('Assessment Sheet'!B91<>"",'Assessment Sheet'!B91,"") | C57: =IF('Assessment Sheet'!C91<>"",'Assessment Sheet'!C91,"") | D57: =IF('Assessment Sheet'!C91<>"",'Assessment Sheet'!D91,"") | E57: =IF('Assessment Sheet'!B91<>"",'Assessment Sheet'!I91,"") | F57: =IF('Assessment Sheet'!J91<>"",'Assessment Sheet'!J91,"") -> 0 | G57: =IF(E57<>"",('Processing Sheet'!#REF!-'Processing Sheet'!#REF!),"") | H57: =IF(G57<>"",G57*D57/100,"")
A58: 12 | B58: =IF('Assessment Sheet'!B92<>"",'Assessment Sheet'!B92,"") | C58: =IF('Assessment Sheet'!C92<>"",'Assessment Sheet'!C92,"") | D58: =IF('Assessment Sheet'!C92<>"",'Assessment Sheet'!D92,"") | E58: =IF('Assessment Sheet'!B92<>"",'Assessment Sheet'!I92,"") | F58: =IF('Assessment Sheet'!J92<>"",'Assessment Sheet'!J92,"") -> 0 | G58: =IF(E58<>"",('Processing Sheet'!#REF!-'Processing Sheet'!#REF!),"") | H58: =IF(G58<>"",G58*D58/100,"")
... A71: 25 | B71: =IF('Assessment Sheet'!B105<>"",'Assessment Sheet'!B105,"") | C71: =IF('Assessment Sheet'!C105<>"",'Assessment Sheet'!C105,"") -> PLASTIC | D71: =IF('Assessment Sheet'!C105<>"",'Assessment Sheet'!D105,"") -> 0.28 | E71: =IF('Assessment Sheet'!B105<>"",'Assessment Sheet'!I105,"") | F71: =IF('Assessment Sheet'!J105<>"",'Assessment Sheet'!J105,"") -> 0 | G71: =IF(E71<>"",('Processing Sheet'!#REF!-'Processing Sheet'!#REF!),"") | H71: =IF(G71<>"",G71*D71/100,"")
A72: NET AMOUNT | E72: =SUM(E47:E71) -> 0 | F72: =SUM(F47:F71) -> 0 | G72: =SUM(G47:G71) -> 0 | H72: =SUM(H47:H71) -> 0
A76: Labour Charges:
A77: Sl No. | B77: Labour Charge for Damaged Parts | C77: Job Type | D77: GST (Service) | E77: Insurance Co.'s Liability | F77: GST | G77: Insured's Liability | H77: GST
A78: 1 | B78: =IF('Assessment Sheet'!B11<>"",'Assessment Sheet'!B11,"") | C78: =IF('Assessment Sheet'!D11<>"",'Assessment Sheet'!D11,"") -> R&R | D78: =IF('Assessment Sheet'!D11<>"",'Assessment Sheet'!E11*100,"") -> 18 | E78: =IF('Assessment Sheet'!I11<>0,'Assessment Sheet'!I11,"") | F78: =IF(E78<>"",E78*D78/100,"") | G78: =IF(E78<>"",'Assessment Sheet'!G11-'Assessment Sheet'!I11,"") | H78: =IF(G78<>"",G78*D78/100,"")
A79: 2 | B79: =IF('Assessment Sheet'!B12<>"",'Assessment Sheet'!B12,"") | C79: =IF('Assessment Sheet'!D12<>"",'Assessment Sheet'!D12,"") -> R&R | D79: =IF('Assessment Sheet'!D12<>"",'Assessment Sheet'!E12*100,"") -> 18 | E79: =IF('Assessment Sheet'!I12<>0,'Assessment Sheet'!I12,"") | F79: =IF(E79<>"",E79*D79/100,"") | G79: =IF(E79<>"",'Assessment Sheet'!G12-'Assessment Sheet'!I12,"") | H79: =IF(G79<>"",G79*D79/100,"")
A80: 3 | B80: =IF('Assessment Sheet'!B13<>"",'Assessment Sheet'!B13,"") | C80: =IF('Assessment Sheet'!D13<>"",'Assessment Sheet'!D13,"") -> Repair/Dent | D80: =IF('Assessment Sheet'!D13<>"",'Assessment Sheet'!E13*100,"") -> 18 | E80: =IF('Assessment Sheet'!I13<>0,'Assessment Sheet'!I13,"") | F80: =IF(E80<>"",E80*D80/100,"") | G80: =IF(E80<>"",'Assessment Sheet'!G13-'Assessment Sheet'!I13,"") | H80: =IF(G80<>"",G80*D80/100,"")
A81: 4 | B81: =IF('Assessment Sheet'!B14<>"",'Assessment Sheet'!B14,"") | C81: =IF('Assessment Sheet'!D14<>"",'Assessment Sheet'!D14,"") | D81: =IF('Assessment Sheet'!D14<>"",'Assessment Sheet'!E14*100,"") | E81: =IF('Assessment Sheet'!I14<>0,'Assessment Sheet'!I14,"") | F81: =IF(E81<>"",E81*D81/100,"") | G81: =IF(E81<>"",'Assessment Sheet'!G14-'Assessment Sheet'!I14,"") | H81: =IF(G81<>"",G81*D81/100,"")
A82: 5 | B82: =IF('Assessment Sheet'!B15<>"",'Assessment Sheet'!B15,"") | C82: =IF('Assessment Sheet'!D15<>"",'Assessment Sheet'!D15,"") | D82: =IF('Assessment Sheet'!D15<>"",'Assessment Sheet'!E15*100,"") | E82: =IF('Assessment Sheet'!I15<>0,'Assessment Sheet'!I15,"") | F82: =IF(E82<>"",E82*D82/100,"") | G82: =IF(E82<>"",'Assessment Sheet'!G15-'Assessment Sheet'!I15,"") | H82: =IF(G82<>"",G82*D82/100,"")
A83: 6 | B83: =IF('Assessment Sheet'!B16<>"",'Assessment Sheet'!B16,"") | C83: =IF('Assessment Sheet'!D16<>"",'Assessment Sheet'!D16,"") | D83: =IF('Assessment Sheet'!D16<>"",'Assessment Sheet'!E16*100,"") | E83: =IF('Assessment Sheet'!I16<>0,'Assessment Sheet'!I16,"") | F83: =IF(E83<>"",E83*D83/100,"") | G83: =IF(E83<>"",'Assessment Sheet'!G16-'Assessment Sheet'!I16,"") | H83: =IF(G83<>"",G83*D83/100,"")
A84: 7 | B84: =IF('Assessment Sheet'!B17<>"",'Assessment Sheet'!B17,"") | C84: =IF('Assessment Sheet'!D17<>"",'Assessment Sheet'!D17,"") | D84: =IF('Assessment Sheet'!D17<>"",'Assessment Sheet'!E17*100,"") | E84: =IF('Assessment Sheet'!I17<>0,'Assessment Sheet'!I17,"") | F84: =IF(E84<>"",E84*D84/100,"") | G84: =IF(E84<>"",'Assessment Sheet'!G17-'Assessment Sheet'!I17,"") | H84: =IF(G84<>"",G84*D84/100,"")
A85: 8 | B85: =IF('Assessment Sheet'!B18<>"",'Assessment Sheet'!B18,"") | C85: =IF('Assessment Sheet'!D18<>"",'Assessment Sheet'!D18,"") | D85: =IF('Assessment Sheet'!D18<>"",'Assessment Sheet'!E18*100,"") | E85: =IF('Assessment Sheet'!I18<>0,'Assessment Sheet'!I18,"") | F85: =IF(E85<>"",E85*D85/100,"") | G85: =IF(E85<>"",'Assessment Sheet'!G18-'Assessment Sheet'!I18,"") | H85: =IF(G85<>"",G85*D85/100,"")
A86: 9 | B86: =IF('Assessment Sheet'!B19<>"",'Assessment Sheet'!B19,"") | C86: =IF('Assessment Sheet'!D19<>"",'Assessment Sheet'!D19,"") | D86: =IF('Assessment Sheet'!D19<>"",'Assessment Sheet'!E19*100,"") | E86: =IF('Assessment Sheet'!I19<>0,'Assessment Sheet'!I19,"") | F86: =IF(E86<>"",E86*D86/100,"") | G86: =IF(E86<>"",'Assessment Sheet'!G19-'Assessment Sheet'!I19,"") | H86: =IF(G86<>"",G86*D86/100,"")
A87: 10 | B87: =IF('Assessment Sheet'!B20<>"",'Assessment Sheet'!B20,"") | C87: =IF('Assessment Sheet'!D20<>"",'Assessment Sheet'!D20,"") | D87: =IF('Assessment Sheet'!D20<>"",'Assessment Sheet'!E20*100,"") | E87: =IF('Assessment Sheet'!I20<>0,'Assessment Sheet'!I20,"") | F87: =IF(E87<>"",E87*D87/100,"") | G87: =IF(E87<>"",'Assessment Sheet'!G20-'Assessment Sheet'!I20,"") | H87: =IF(G87<>"",G87*D87/100,"")
A88: 11 | B88: =IF('Assessment Sheet'!B21<>"",'Assessment Sheet'!B21,"") | C88: =IF('Assessment Sheet'!D21<>"",'Assessment Sheet'!D21,"") | D88: =IF('Assessment Sheet'!D21<>"",'Assessment Sheet'!E21*100,"") | E88: =IF('Assessment Sheet'!I21<>0,'Assessment Sheet'!I21,"") | F88: =IF(E88<>"",E88*D88/100,"") | G88: =IF(E88<>"",'Assessment Sheet'!G21-'Assessment Sheet'!I21,"") | H88: =IF(G88<>"",G88*D88/100,"")
A89: 12 | B89: =IF('Assessment Sheet'!B22<>"",'Assessment Sheet'!B22,"") | C89: =IF('Assessment Sheet'!D22<>"",'Assessment Sheet'!D22,"") | D89: =IF('Assessment Sheet'!D22<>"",'Assessment Sheet'!E22*100,"") | E89: =IF('Assessment Sheet'!I22<>0,'Assessment Sheet'!I22,"") | F89: =IF(E89<>"",E89*D89/100,"") | G89: =IF(E89<>"",'Assessment Sheet'!G22-'Assessment Sheet'!I22,"") | H89: =IF(G89<>"",G89*D89/100,"")
... A102: 25 | B102: =IF('Assessment Sheet'!B35<>"",'Assessment Sheet'!B35,"") | C102: =IF('Assessment Sheet'!D35<>"",'Assessment Sheet'!D35,"") | D102: =IF('Assessment Sheet'!D35<>"",'Assessment Sheet'!E35*100,"") | E102: =IF('Assessment Sheet'!I35<>0,'Assessment Sheet'!I35,"") | F102: =IF(E102<>"",E102*D102/100,"") | G102: =IF(E102<>"",'Assessment Sheet'!G35-'Assessment Sheet'!I35,"") | H102: =IF(G102<>"",G102*D102/100,"")
A103: NET AMOUNT | E103: =SUM(E78:E102) -> 0 | F103: =SUM(F78:F102) -> 0 | G103: =SUM(G78:G102) -> 0 | H103: =SUM(H78:H102) -> 0
A105: Labour Charges For Painting Only :
A106: Sl No. | B106: List of Damaged Parts | C106: Job Type | D106: GST (Service) | E106: Insurance Co.'s Liability | F106: GST | G106: Insured's Liability | H106: GST
A107: 1 | B107: =IF('Assessment Sheet'!B45<>"",'Assessment Sheet'!B45,"") | C107: =IF(B107<>"","Painting","") | D107: =IF(B107<>"",'Assessment Sheet'!E45*100,"") | E107: =IF('Assessment Sheet'!I45<>0,IF('Assessment Sheet'!$G$71="Yes",'Assessment Sheet'!I45*0.75,'Assessment Sheet'!I45),"") | F107: =IF(E107<>"",E107*D107/100,"") | G107: =IF(E107<>"",,"") | H107: =IF(G107<>"",G107*D107/100,"")
A108: 2 | B108: =IF('Assessment Sheet'!B46<>"",'Assessment Sheet'!B46,"") | C108: =IF(B108<>"","Painting","") | D108: =IF(B108<>"",'Assessment Sheet'!E46*100,"") | E108: =IF('Assessment Sheet'!I46<>0,IF('Assessment Sheet'!$G$71="Yes",'Assessment Sheet'!I46*0.75,'Assessment Sheet'!I46),"") | F108: =IF(E108<>"",E108*D108/100,"") | G108: =IF(E108<>"",'Assessment Sheet'!G46-'Assessment Sheet'!I46,"") | H108: =IF(G108<>"",G108*D108/100,"")
A109: 3 | B109: =IF('Assessment Sheet'!B47<>"",'Assessment Sheet'!B47,"") | C109: =IF(B109<>"","Painting","") | D109: =IF(B109<>"",'Assessment Sheet'!E47*100,"") | E109: =IF('Assessment Sheet'!I47<>0,IF('Assessment Sheet'!$G$71="Yes",'Assessment Sheet'!I47*0.75,'Assessment Sheet'!I47),"") | F109: =IF(E109<>"",E109*D109/100,"") | G109: =IF(E109<>"",'Assessment Sheet'!G47-'Assessment Sheet'!I47,"") | H109: =IF(G109<>"",G109*D109/100,"")
A110: 4 | B110: =IF('Assessment Sheet'!B48<>"",'Assessment Sheet'!B48,"") | C110: =IF(B110<>"","Painting","") | D110: =IF(B110<>"",'Assessment Sheet'!E48*100,"") | E110: =IF('Assessment Sheet'!I48<>0,IF('Assessment Sheet'!$G$71="Yes",'Assessment Sheet'!I48*0.75,'Assessment Sheet'!I48),"") | F110: =IF(E110<>"",E110*D110/100,"") | G110: =IF(E110<>"",'Assessment Sheet'!G48-'Assessment Sheet'!I48,"") | H110: =IF(G110<>"",G110*D110/100,"")
A111: 5 | B111: =IF('Assessment Sheet'!B49<>"",'Assessment Sheet'!B49,"") | C111: =IF(B111<>"","Painting","") | D111: =IF(B111<>"",'Assessment Sheet'!E49*100,"") | E111: =IF('Assessment Sheet'!I49<>0,IF('Assessment Sheet'!$G$71="Yes",'Assessment Sheet'!I49*0.75,'Assessment Sheet'!I49),"") | F111: =IF(E111<>"",E111*D111/100,"") | G111: =IF(E111<>"",'Assessment Sheet'!G49-'Assessment Sheet'!I49,"") | H111: =IF(G111<>"",G111*D111/100,"")
A112: 6 | B112: =IF('Assessment Sheet'!B50<>"",'Assessment Sheet'!B50,"") | C112: =IF(B112<>"","Painting","") | D112: =IF(B112<>"",'Assessment Sheet'!E50*100,"") | E112: =IF('Assessment Sheet'!I50<>0,IF('Assessment Sheet'!$G$71="Yes",'Assessment Sheet'!I50*0.75,'Assessment Sheet'!I50),"") | F112: =IF(E112<>"",E112*D112/100,"") | G112: =IF(E112<>"",'Assessment Sheet'!G50-'Assessment Sheet'!I50,"") | H112: =IF(G112<>"",G112*D112/100,"")
A113: 7 | B113: =IF('Assessment Sheet'!B51<>"",'Assessment Sheet'!B51,"") | C113: =IF(B113<>"","Painting","") | D113: =IF(B113<>"",'Assessment Sheet'!E51*100,"") | E113: =IF('Assessment Sheet'!I51<>0,IF('Assessment Sheet'!$G$71="Yes",'Assessment Sheet'!I51*0.75,'Assessment Sheet'!I51),"") | F113: =IF(E113<>"",E113*D113/100,"") | G113: =IF(E113<>"",'Assessment Sheet'!G51-'Assessment Sheet'!I51,"") | H113: =IF(G113<>"",G113*D113/100,"")
A114: 8 | B114: =IF('Assessment Sheet'!B52<>"",'Assessment Sheet'!B52,"") | C114: =IF(B114<>"","Painting","") | D114: =IF(B114<>"",'Assessment Sheet'!E52*100,"") | E114: =IF('Assessment Sheet'!I52<>0,IF('Assessment Sheet'!$G$71="Yes",'Assessment Sheet'!I52*0.75,'Assessment Sheet'!I52),"") | F114: =IF(E114<>"",E114*D114/100,"") | G114: =IF(E114<>"",'Assessment Sheet'!G52-'Assessment Sheet'!I52,"") | H114: =IF(G114<>"",G114*D114/100,"")
A115: 9 | B115: =IF('Assessment Sheet'!B53<>"",'Assessment Sheet'!B53,"") | C115: =IF(B115<>"","Painting","") | D115: =IF(B115<>"",'Assessment Sheet'!E53*100,"") | E115: =IF('Assessment Sheet'!I53<>0,IF('Assessment Sheet'!$G$71="Yes",'Assessment Sheet'!I53*0.75,'Assessment Sheet'!I53),"") | F115: =IF(E115<>"",E115*D115/100,"") | G115: =IF(E115<>"",'Assessment Sheet'!G53-'Assessment Sheet'!I53,"") | H115: =IF(G115<>"",G115*D115/100,"")
A116: 10 | B116: =IF('Assessment Sheet'!B54<>"",'Assessment Sheet'!B54,"") | C116: =IF(B116<>"","Painting","") | D116: =IF(B116<>"",'Assessment Sheet'!E54*100,"") | E116: =IF('Assessment Sheet'!I54<>0,IF('Assessment Sheet'!$G$71="Yes",'Assessment Sheet'!I54*0.75,'Assessment Sheet'!I54),"") | F116: =IF(E116<>"",E116*D116/100,"") | G116: =IF(E116<>"",'Assessment Sheet'!G54-'Assessment Sheet'!I54,"") | H116: =IF(G116<>"",G116*D116/100,"")
A117: 11 | B117: =IF('Assessment Sheet'!B55<>"",'Assessment Sheet'!B55,"") | C117: =IF(B117<>"","Painting","") | D117: =IF(B117<>"",'Assessment Sheet'!E55*100,"") | E117: =IF('Assessment Sheet'!I55<>0,IF('Assessment Sheet'!$G$71="Yes",'Assessment Sheet'!I55*0.75,'Assessment Sheet'!I55),"") | F117: =IF(E117<>"",E117*D117/100,"") | G117: =IF(E117<>"",'Assessment Sheet'!G55-'Assessment Sheet'!I55,"") | H117: =IF(G117<>"",G117*D117/100,"")
A118: 12 | B118: =IF('Assessment Sheet'!B56<>"",'Assessment Sheet'!B56,"") | C118: =IF(B118<>"","Painting","") | D118: =IF(B118<>"",'Assessment Sheet'!E56*100,"") | E118: =IF('Assessment Sheet'!I56<>0,IF('Assessment Sheet'!$G$71="Yes",'Assessment Sheet'!I56*0.75,'Assessment Sheet'!I56),"") | F118: =IF(E118<>"",E118*D118/100,"") | G118: =IF(E118<>"",'Assessment Sheet'!G56-'Assessment Sheet'!I56,"") | H118: =IF(G118<>"",G118*D118/100,"")
A119: 13 | B119: =IF('Assessment Sheet'!B57<>"",'Assessment Sheet'!B57,"") | C119: =IF(B119<>"","Painting","") | D119: =IF(B119<>"",'Assessment Sheet'!E57*100,"") | E119: =IF('Assessment Sheet'!I57<>0,IF('Assessment Sheet'!$G$71="Yes",'Assessment Sheet'!I57*0.75,'Assessment Sheet'!I57),"") | F119: =IF(E119<>"",E119*D119/100,"") | G119: =IF(E119<>"",'Assessment Sheet'!G57-'Assessment Sheet'!I57,"") | H119: =IF(G119<>"",G119*D119/100,"")
... A121: 15 | B121: =IF('Assessment Sheet'!B59<>"",'Assessment Sheet'!B59,"") | C121: =IF(B121<>"","Painting","") | D121: =IF(B121<>"",'Assessment Sheet'!E59*100,"") | E121: =IF('Assessment Sheet'!I59<>0,IF('Assessment Sheet'!$G$71="Yes",'Assessment Sheet'!I59*0.75,'Assessment Sheet'!I59),"") | F121: =IF(E121<>"",E121*D121/100,"") | G121: =IF(E121<>"",'Assessment Sheet'!G59-'Assessment Sheet'!I59,"") | H121: =IF(G121<>"",G121*D121/100,"")
A122: NET AMOUNT | E122: =SUM(E107:E121) -> 0 | F122: =SUM(F107:F121) -> 0 | G122: =SUM(G107:G121) -> 0 | H122: =SUM(H107:H121) -> 0
A124: SL NO | B124: DESCRIPTION | F124: Assessment | H124: Customer
A125: 1 | B125: COST OF PAINT MATERIAL | F125: =MAX(E44,E45) -> 0 | H125: =MAX(G44,G45) -> #REF!
A126: 2 | B126: REPLACEMENT OF PARTS | F126: =E72 -> 0 | H126: =G72 -> 0
A127: 3 | B127: LABOUR CHARGES | F127: =E103 -> 0 | H127: =G103 -> 0
A128: 4 | B128: PAINTING CHARGES | F128: =E122 -> 0 | H128: =G122 -> 0
A129: 5 | B129: TOWING CHARGES | F129: ='Processing Sheet'!H49 -> 0
A130: 6 | B130: GST | F130: =MAX(F44,F45)+F72+F103+F122 -> 0 | H130: =MAX(H44,H45)+H72+H103+H122 -> #REF!
A131: 7 | B131: SUB TOTAL | F131: =SUM(F125:F130) -> 0 | H131: =SUM(H125:H130) -> #REF!
A132: 8 | B132: Nil Depreciation Excess (5% of Claim Amount) If Applicable | E132: ='Processing Sheet'!F52 -> No | F132: ='Processing Sheet'!H52 -> 0
A133: 9 | B133: SALVAGE VALUE(IF APPLICABLE) | F133: ='Processing Sheet'!H53 -> 0 | H133: ='Processing Sheet'!H53 -> 0
A134: 10 | B134: COMPULSORY STANDARD EXCESS | F134: ='Processing Sheet'!H54 -> 1000 | H134: ='Processing Sheet'!H54 -> 1000
A135: 11 | B135: IMPOSED EXCESS | F135: ='Processing Sheet'!H55 -> 0 | H135: ='Processing Sheet'!H55 -> 0
A136: 12 | B136: VOLUNTARY EXCESS | F136: ='Processing Sheet'!H56 -> 0 | H136: ='Processing Sheet'!H56 -> 0
A137: 13 | B137: ROUND OFF | F137: ='Processing Sheet'!H57 -> 0
A138: TOTAL(ROUNDED OFF) | F138: =ROUND(F131-SUM(F132:F137),0) -> -1000 | H138: =ROUND(H131+SUM(H132:H137),0) -> #REF!
A139: Pre-Invoice Amount | C139: ='Processing Sheet'!D60 -> 23047 | E139: FINAL ASSESSMENT | F139: ='Processing Sheet'!H59 -> -1000
A140: Customer's Liability | C140: ='Processing Sheet'!D59 -> 0

Sheet Data Entry
A1: Policy Details: | F1: Reference Number | H1: DKS/ Aasth Honda/March/2024-2025
A2: TIEUP PARTNER | B2: MARUTI | F2: Survey Fee Invoice Number | H2: Report-0000/24-25
A3: CLAIM NUMBER | F3: Date of Report
A4: POLICY NUMBER
A5: NAME OF INSURED | B5: Mr. | F5: Total No of Survey Jobs Allotted | H5: 1
A6: INSURED'S PHONE NO. | F6: City Name | H6: Patna
A7: INSURED'S Email ID | F7: Class of City | H7: A
A8: TYPE OF PRIVATE VEHICLE | B8: PRIVATE CAR
A9: FINANCER NAME
A10: PERIOD OF INSURANCE | C10: To | F10: Policy Status | G10: =IF(L16>1,IF(AND(HOUR(B10)>0,L16>1),"Break Insurance","Non-Break Insurance"),"New Policy") -> New Policy
A11: IDV OF VEHICLE | F11: Developed by SAATH, Patna.
A12: NO. OF CLAIM(S) | B12: 1 | F12: Strategic Alliance Auto Tie-up Hub, “Jeevan Prakash”, Fraser Road, Patna- 800001, Bihar
A13: IMT ENDORSEMENT | B13: 7,10,28,16
A14: IMPOSED EXCESS | B14: 0
A15: VOLUNTARY EXCESS | B15: 0 | F15: Whether Engine Protect Endorsement ? | I15: Yes
A16: COMPULSORY EXCESS | B16: =IF(B5="","",E112) -> 1000 | F16: Whether Zero Depreciation Endorsement ? | I16: Yes | J16: Age of Vehicle | L16: =ROUND((B38-MIN(B19,B20))/365,2) -> 0
A17: Vehicle Details: | F17: Zero Depreciation Applicable | I17: =IF(I16="Yes",IF(B12>2,"No","Yes"),"No") -> Yes
A18: Registration Number | F18: For Nil Depreciation Policy Please select Yes From above Dropdown List. -SAATH Tieup Claims: Select Yes from above Dropdown List and its done. -Claim Hub Claims: Select Yes from above and don't forget to select 'Yes' from dropdown in Assessment Sheet as 5% of claim amount is applicable.
A19: Registration Date
A20: Vehicle Sale Date
A21: Chassis Number
A22: Engine Number
A23: Make/Model | B23: M/S Maruti
A24: Colour of Vehicle | F24: Whether Key & lock Protect Endorsement ? | I24: No
A25: Permit No. | B25: NA | F25: Whether Consumables Protect Endorsement ? | I25: No
A26: Permit Authorised by | B26: NA | F26: Whether Invoice Protect Endorsement ? | I26: No
A27: Permit Validity | B27: NA | C27: To | F27: Whether CNG Protect Endorsement in RC,POLICY,PERMIT ? | I27: No
A28: Fitness Validity | C28: To | F28: Whether case of BREAK INSURANCE,Taken break report and photographs ? | I28: No
A29: Load Challan Detail | B29: NA | F29: Whether Third party insurance valid ? | I29: Yes
A30: Cubic Capacity | D30: cc
A31: Unladen Weight (GVW) | D31: Kgs | F31: Abbreviations for Licence in India:
A32: Tax Paid Upto | B32: Road-Worthy | F32: Two wheel:
A33: Type of body | B33: Saloon | F33: MC or MCWOG: Motorcycle Without Gear
A34: Pre-Accident Condition | B34: Road-Worthy | F34: MCWG or M/CYCL.WG: Motorcycle With Gear
A35: Seating Capacity/Passenger | B35: 5 | C35: Persons
A36: 64 VB Compliance | B36: Yes | F36: Three/four wheel:
A37: Accident Details | F37: ARNT: Auto Rickshaw – Non Transport
A38: Date of accident | C38: at | F38: ART: Auto Rickshaw – Transport
A39: Place of accident | F39: LMV-NT: Light Motor Vehicle – Non Transport
A40: Date of intimation | F40: LMV-T: Light Motor Vehicle – Transport
A41: Estimated Loss | F41: MGV: Medium Goods Vehicle
A42: Assessed Loss | F42: MPV: Medium Passenger Vehicle
A43: Deputation of survey
A44: Date of survey | F44: Heavy Motor Vehicle:
A45: Place of survey | B45: Aastha Honda Patna | F45: HGV: Heavy Good Vehicle
A46: Cause of loss | B46: As per statement of insured and also mentioned in the claim form. While the insured vehicle was en-route. At the place of accident , . Hence the damages sustained. | F46: HPV: Heavy Passenger Vehicle
F47: HTV: Heavy Transport Vehicle (Valid for Goods and Passenger Vehicles)
F48: HZRD: Heavy Transport Vehicle with Hazardous materials
A49: Is there any FIR? | B49: No | F49: TR: Tractor
A50: Spot Survey Date(Optional) | F50: RDRLR: Road Roller
A51: Reinspection Date(Optional) | F51: Driving License Type
A52: Driver Details | F52: MCWG : Motor Cycle with Gear
A53: Driver name | F53: MCOW : Motor Cycle without Gear
A54: Driving licence number | F54: LMV : Light Motor Vehicle (Pvt)
A55: Valid upto | F55: LMV : Light Motor Vehicle (Prof)
A56: Issued on | F56: LMV-NT : Light Motor Vehicle - Non Transport)
A57: Issuing Authority | B57: D.T.O Patna | F57: LMV-T : Light Motor Vehicle - Transport
A58: Type of License | B58: MCWG/LMV : Light Motor Vehicle & Motor Cycle with Gear | F58: HMV : Heavy Motor Vehicle
A59: Surveyor's Detail: | F59: MCWG/LMV : Light Motor Vehicle & Motor Cycle with Gear
A60: Surveyor's Name | B60: Dilip Kumar Sinha | F60: MCWG/LMV : Light Motor Vehicle(Prof) & Motor Cycle with Gear
A61: Address Line | B61: =VLOOKUP(B60,'Surveyor''s Master'!B2:N30,2,FALSE) -> V/477, Vidyapuri, Kankarbagh, Patna-800020 | F61: Others
A63: Mobile Number | B63: =VLOOKUP(B60,'Surveyor''s Master'!B2:N30,3,FALSE) -> 9334110636
A64: Telephone Number | B64: =VLOOKUP(B60,'Surveyor''s Master'!B2:N30,4,FALSE) -> 0 | F64: Type of Material
A65: Email Id | B65: =VLOOKUP(B60,'Surveyor''s Master'!B2:N30,5,FALSE) -> dilipsinha11k@gmail.com | F65: FRP | G65: 0
A66: License Number | B66: =VLOOKUP(B60,'Surveyor''s Master'!B2:N30,6,FALSE) -> 63315 | F66: GLASS | G66: 0
A67: Date of Expiry | B67: 46469 | F67: METAL | G67: ='Processing Sheet'!E31 -> 0
A68: Bank Name | B68: =VLOOKUP(B60,'Surveyor''s Master'!B2:N30,9,FALSE) -> State Bank of India | F68: PLASTIC | G68: 50
A69: Branch | B69: =VLOOKUP(B60,'Surveyor''s Master'!B2:N30,10,FALSE) -> Hanuman Nagar Br. | F69: RUBBER | G69: 50
A70: IFSC Code | B70: =VLOOKUP(B60,'Surveyor''s Master'!B2:N30,11,FALSE) -> SBIN0009005 | F70: FIBER | G70: 30
A71: Bank A/c Number | B71: =VLOOKUP(B60,'Surveyor''s Master'!B2:N30,12,FALSE) -> 20019295926 | G71: 30
A72: PAN Detail | B72: =VLOOKUP(B60,'Surveyor''s Master'!B2:N30,13,FALSE) -> APZPS2395Q
A73: GSTIN | B73: =VLOOKUP(B60,'Surveyor''s Master'!B2:N30,7,FALSE) -> Not Appiled
A75: User can Modify This
A76: GST (Parts) | B76: GST (Service)
A77: 0 | B77: 0.18
A78: 0.05
A79: 0.12
A80: 0.18
A81: 0.28 | F81: Please Use apostrophe ' followed by Account Number. For e.g: '0459053000100705
A89: POLICY EXCESS CALCULATION LOGIC
A90: PRIVATE CAR | B90: 1 | C90: =A90&B90 -> PRIVATE CAR1 | E90: 1000 | F90: UPTO 1500
A91: PRIVATE CAR | B91: 2 | C91: =A91&B91 -> PRIVATE CAR2 | E91: 2000 | F91: > 1500
A92: TAXI | B92: 1 | C92: =A92&B92 -> TAXI1 | E92: 500
A93: TAXI | B93: 2 | C93: =A93&B93 -> TAXI2 | E93: 1000
A94: AMBULANCE | B94: 1 | C94: =A94&B94 -> AMBULANCE1 | E94: 2000
A95: AMBULANCE | B95: 2 | C95: =A95&B95 -> AMBULANCE2 | E95: =ROUND(0.5*B105/100,0) -> 0
A96: GOODS CARRYING VEHICLE | B96: 1 | C96: =A96&B96 -> GOODS CARRYING VEHICLE1 | E96: 500 | F96: <=7500 Kg
A97: GOODS CARRYING VEHICLE | B97: 2 | C97: =A97&B97 -> GOODS CARRYING VEHICLE2 | E97: 1000 | F97: 7501-16500
A98: GOODS CARRYING VEHICLE | B98: 3 | C98: =A98&B98 -> GOODS CARRYING VEHICLE3 | E98: 1500 | F98: >16500
A99: PASSENGER CARRYING VEHICLE | B99: 1 | C99: =A99&B99 -> PASSENGER CARRYING VEHICLE1 | E99: 500 | F99: <=17 Passenger
A100: PASSENGER CARRYING VEHICLE | B100: 2 | C100: =A100&B100 -> PASSENGER CARRYING VEHICLE2 | E100: 1000 | F100: 18-36
A101: PASSENGER CARRYING VEHICLE | B101: 3 | C101: =A101&B101 -> PASSENGER CARRYING VEHICLE3 | E101: 1500 | F101: >36
A102: TWO WHEELER | B102: 1 | C102: =A102&B102 -> TWO WHEELER1 | E102: 100
A104: POLICY EXCESS CALCULATION
A105: IDV | B105: =B11 -> 0
A106: =B8 -> PRIVATE CAR
A107: Passenger | B107: =#REF! -> #REF!
A108: Cc | B108: =B30 -> 0
A109: GVW | B109: =B31 -> 0
A111: Excess Code | B111: Mixed Code | E111: Excess
...

Sheet Status Report
A1: ='Data Entry'!$B$60 -> Dilip Kumar Sinha | C1: ='Data Entry'!$B$61 -> V/477, Vidyapuri, Kankarbagh, Patna-800020
A2: SURVEYOR/LOSS ASSESSOR/VALUER | D2: Mobile Number | E2: ='Data Entry'!$B$63 -> 9334110636 | G2: Developed by SAATH, Patna.
A3: License No | B3: ='Data Entry'!$B$66 -> 63315 | D3: Date of Expiry | E3: ='Data Entry'!$B$67 -> 46469
A4: Email Id | B4: ='Data Entry'!$B$65 -> dilipsinha11k@gmail.com | D4: Telephone No | E4: ='Data Entry'!$B$64 -> 0
A5: STATUS REPORT
A6: PLACE OF SURVEY | C6: ='Data Entry'!$B$45 -> Aastha Honda Patna
A7: DATE OF SURVEY | C7: ='Data Entry'!$B$44 -> 0
A8: ='Data Entry'!$B$8 -> PRIVATE CAR
A9: 1 | B9: ='Data Entry'!$A$3 -> CLAIM NUMBER | C9: ='Data Entry'!$B$3 -> 0
A10: 2 | B10: ='Data Entry'!$A$4 -> POLICY NUMBER | C10: ='Data Entry'!$B$4 -> 0
A11: 3 | B11: NAME OF INSURED | C11: ='Data Entry'!$B$5 -> Mr.
A12: 4 | B12: VEHICLE NO. | C12: ='Data Entry'!$B$18 -> 0
A13: 5 | B13: NO. OF CLAIM(S) | C13: ='Data Entry'!$B$12 -> 1
A14: 6 | B14: ='Data Entry'!$A$8 -> TYPE OF PRIVATE VEHICLE | C14: ='Data Entry'!$B$8 -> PRIVATE CAR
A15: 7 | B15: PERIOD OF INSURANCE | C15: ='Data Entry'!B10 -> 0 | D15: ='Data Entry'!C10 -> To | E15: ='Data Entry'!D10 -> 0
A16: 8 | B16: PLACE OF ACCIDENT | C16: ='Data Entry'!$B$39 -> 0
A17: 9 | B17: VEHICLE SALE DATE | C17: ='Data Entry'!$B$20 -> 0
A18: 10 | B18: DATE OF LOSS | C18: ='Data Entry'!$B$38 -> 0
A19: 11 | B19: DATE OF INTIMATION | C19: ='Data Entry'!$B$40 -> 0
A20: 12 | B20: EXPECTED DATE OF DELIVERY OF ACCIDENTED VEHICLE
A21: 13 | B21: CAUSE OF LOSS | C21: ='Data Entry'!$B$46 -> As per statement of insured and also mentioned in the claim form. While the insured vehicle was en-route. At the place of accident , . Hence the damages sustained.
A22: 14 | B22: DRIVER'S NAME | C22: ='Data Entry'!$B$53 -> 0
A23: 15 | B23: ESTIMATED LOSS | C23: ='Data Entry'!$B$41 -> 0
A24: 16 | B24: ASSESSED VALUE | C24: ='Processing Sheet'!$H$58 -> -1000
A25: 17 | B25: PROFESSIONAL FEE | C25: ='Surveyor Fee'!$E$39 -> 750
A26: 18 | B26: SURVEYOR'S COMMENTS ON DISALLOWED/WEAR & TEAR/OLD DAMAGES | C26: NO
A27: 19 | B27: Remarks, if any | C27: NO
A28: 20 | B28: DOCUMENT VERIFIED? | C28: DRIVING LICENSE | E28: YES
C29: REGISTRATION CERTIFICATE/TAX TOKEN | E29: YES
C30: POLICY COPY | E30: YES
C31: PERMIT | E31: NO
C32: LOAD CHALLAN | E32: NO
C33: 64VB | E33: YES
C34: BREAK INSPECTION REPORT APPLICABLE? | E34: =IF('Data Entry'!G10="Break Insurance","Yes","No") -> No | G34: Is Break Inspection Report attached? | K34: NO
C35: AADHAAR CARD | E35: YES
C36: PAN CARD | E36: YES
A37: =IF('Data Entry'!$B$49="Yes","FIR Lodged; Driving Licence is required to be verified.","No FIR Lodged.") -> No FIR Lodged.
A39: NAME OF SURVEYOR | C39: ='Data Entry'!$B$60 -> Dilip Kumar Sinha
C41: Submitted to National Insurance Company Limited

Sheet Processing Sheet
C1: NATIONAL INSURANCE COMPANY LTD. Assessment Sheet
A5: SAATH, Patna | I5: VER 4.3 | J5: Dt. 29/11/22
A6: =IF('Data Entry'!$B$2<>"",'Data Entry'!$B$2,"") -> MARUTI
A7: REFERENCE NUMBER | C7: =IF('Data Entry'!$H$1<>"",'Data Entry'!$H$1,"") -> DKS/ Aasth Honda/March/2024-2025 | G7: DATE OF REPORT | I7: =IF('Data Entry'!$H$3<>"",'Data Entry'!$H$3,"")
A8: TYPE OF SURVEY | C8: SPOT SURVEY | F8: FINAL SURVEY | I8: RE-INSPECTION
A9: SURVEYOR | F9: =IF('Data Entry'!$B$60<>"",'Data Entry'!$B$60,"") -> Dilip Kumar Sinha
A10: DATE OF SURVEY | C10: =IF('Data Entry'!$B$50<>"",'Data Entry'!$B$50,"") | F10: =IF('Data Entry'!$B$44<>"",'Data Entry'!$B$44,"") | I10: =IF('Data Entry'!$B$51<>"",'Data Entry'!$B$51,"")
A11: PLACE OF SURVEY | F11: ='Data Entry'!$B$45 -> Aastha Honda Patna
G12: PRINTING DATE | I12: =TODAY() -> 46137
A13: POLICY DETAILS: | E13: =IF('Data Entry'!G10<>"",'Data Entry'!G10) -> New Policy | J13: =IF('Data Entry'!I17="No","Normal Policy","Zero Dep.Policy") -> Zero Dep.Policy
A14: INSURED | C14: ='Data Entry'!$B$5 -> Mr. | G14: TYPE OF POLICY | I14: ='Data Entry'!$B$8 -> PRIVATE CAR
A15: PERIOD OF INSURANCE | C15: =IF('Data Entry'!$B$10<>"",'Data Entry'!$B$10,"") | E15: TO | F15: =IF('Data Entry'!$D$10<>"",'Data Entry'!$D$10,"") | G15: ='Data Entry'!$A$3 -> CLAIM NUMBER | I15: ='Data Entry'!$B$3 -> 0
A16: POLICY NO. | C16: ='Data Entry'!$B$4 -> 0 | G16: IDV OF VEHICLE | I16: ='Data Entry'!B11 -> 0
A18: VEHICLE DETAILS: | J18: =PROPER('Data Entry'!B8) -> Private Car
A19: REGISTRATION DATE | C19: =IF('Data Entry'!$B$19<>"",'Data Entry'!$B$19,"") | E19: TO | F19: =IF('Data Entry'!$B$32<>"",'Data Entry'!$B$32,"") -> Road-Worthy | G19: REGISTRATION NO. | I19: ='Data Entry'!$B$18 -> 0
A20: CHASSIS NUMBER | C20: ='Data Entry'!$B$21 -> 0 | E20: ENGINE NO | F20: ='Data Entry'!$B$22 -> 0 | G20: MAKE/MODEL | I20: ='Data Entry'!$B$23 -> M/S Maruti
A22: DRIVERS DETAILS: | J22: =IF('Data Entry'!I15="Yes","Engine Protected Policy","") -> Engine Protected Policy
A23: NAME OF DRIVER | C23: ='Data Entry'!$B$53 -> 0 | G23: M.D.L NUMBER | I23: ='Data Entry'!$B$54 -> 0 | L23: Developed by SAATH, Patna.
A24: DATE OF ISSUE | C24: =IF('Data Entry'!$B$56<>"",'Data Entry'!$B$56,"") | E24: TO | F24: =IF('Data Entry'!$B$55<>"",'Data Entry'!$B$55,"")
A25: TYPE OF LICENSE | C25: ='Data Entry'!$B$58 -> MCWG/LMV : Light Motor Vehicle & Motor Cycle with Gear
A27: CLAIM DETAILS: | J27: ='Data Entry'!C38 -> at
A28: DATE OF ACCIDENT | C28: =IF('Data Entry'!$B$38<>"",'Data Entry'!$B$38,"") | G28: INTIMATION DATE | I28: =IF('Data Entry'!$B$40<>"",'Data Entry'!$B$40,"")
A29: PLACE OF ACCIDENT | C29: ='Data Entry'!$B$39 -> 0 | G29: ESTIMATED LOSS | I29: ='Data Entry'!$B$41 -> 0
A31: DEPRECIATION APPLICABLE FOR METAL PARTS : | E31: =IF(I31>10,50,IF(I31>5,40,IF(I31>4,35,IF(I31>3,25,IF(I31>2,15,IF(I31>1,10,IF(I31>0.5,5,0))))))) -> 0 | F31: % | G31: AGE OF VEHICLE | I31: =ROUND('Data Entry'!L16,2) -> 0 | J31: YEARS | L31: =IF(('Data Entry'!B19)<('Data Entry'!B10),YEARFRAC('Data Entry'!B38,'Data Entry'!B19),YEARFRAC('Data Entry'!B38,'Data Entry'!B10)) -> 0
A33: GST DETAILS:
D34: GST (Labour) | F34: Taxable Amount
D35: ='Data Entry'!B77 -> 0.18 | F35: ='Assessment Sheet'!H199 -> 0
D37: GST (Parts) | F37: Taxable Amount
D38: ='Data Entry'!A77 -> 0 | F38: ='Assessment Sheet'!H191 -> 0
D39: ='Data Entry'!A78 -> 0.05 | F39: ='Assessment Sheet'!H192 -> 0
D40: ='Data Entry'!A79 -> 0.12 | F40: ='Assessment Sheet'!H193 -> 0
D41: ='Data Entry'!A80 -> 0.18 | F41: ='Assessment Sheet'!H194 -> 0
D42: ='Data Entry'!A81 -> 0.28 | F42: ='Assessment Sheet'!H195 -> 0
A44: SL NO | B44: DESCRIPTION | H44: AMOUNTS
A45: 1 | B45: COST OF PAINT MATERIAL | H45: =IF('Assessment Sheet'!G71="Yes",'Assessment Sheet'!I79,'Assessment Sheet'!I80) -> 0
A46: 2 | B46: REPLACEMENT OF PARTS | H46: ='Assessment Sheet'!I180-H45 -> 0
A47: 3 | B47: LABOUR CHARGES | H47: ='Assessment Sheet'!$I$41 -> 0
A48: 4 | B48: PAINTING CHARGES | H48: ='Assessment Sheet'!$G$72 -> 0
A49: 5 | B49: TOWING CHARGES
A50: 6 | B50: GST | H50: ='Assessment Sheet'!$G$73+'Assessment Sheet'!$J$41+'Assessment Sheet'!J179 -> 0
A51: 7 | B51: SUB TOTAL | H51: =SUM(H45:J50) -> 0
A52: 8 | B52: Nil Depr. Excess (5% of Claim Amount) If Applicable | F52: No | H52: =IF('Data Entry'!I17="No",0,IF(F52="No",0,IF(AND('Data Entry'!I17="Yes",F52="Yes"),IF('Data Entry'!B8="PRIVATE CAR",MAX(500,MIN(ROUND(H51*0.05,0),2500)),IF('Data Entry'!B8="TWO WHEELER",MAX(250,MIN(ROUND(H51*0.05,0),1000)),0))))) -> 0
A53: 9 | B53: SALVAGE VALUE(IF APPLICABLE)
A54: 10 | B54: COMPULSORY STANDARD EXCESS | H54: ='Data Entry'!$B$16 -> 1000
A55: 11 | B55: IMPOSED EXCESS | H55: ='Data Entry'!$B$14 -> 0
A56: 12 | B56: VOLUNTARY EXCESS | H56: ='Data Entry'!$B$15 -> 0
A57: 13 | B57: ROUND OFF
A58: INVOICE TYPE | D58: Pre-Invoice | G58: TOTAL (ROUNDED OFF) | H58: =IF((H51-SUM(H52:J57))>I16,"Assessment Exceeds IDV",(H51-SUM(H52:J57))) -> -1000
A59: Customer Money Receipt Amount | F59: FINAL ASSESSMENT | H59: =IF((H51-SUM(H52:J57))>I16,"Assessment Exceeds IDV",ROUND(MIN(H58,(D60-D59)),0)) -> -1000
A60: =IF(D58="Pre-Invoice","Pre-Invoice Amount", "Invoice Amount") -> Pre-Invoice Amount | D60: 23047
A61: =IF(D58="Pre-Invoice","Pre-Invoice Number", "Invoice Number") -> Pre-Invoice Number | D61: JC25001035 | F61: =IF(D58="Pre-Invoice","Pre-Invoice Date", "Invoice Date") -> Pre-Invoice Date | I61: 45977
A62: =IF(D58="Pre-Invoice","Customer's Liability ","Difference in Assesment ") -> Customer's Liability | I62: =(D60-D59)-H58 -> 24047
A63: Comments | C63: Because insured payment
A64: Submitted to National Insurance Company Limited
A66: Passed For Payment
A67: Rs_______________
A71: Competant Authority

Sheet Surveyor Fee
A1: SURVEY FEE BILL
A3: INVOICE NUMBER | B3: ='Data Entry'!$H2 -> Report-0000/24-25 | C3: GSTIN | D3: ='Data Entry'!B73 -> Not Appiled
A4: REFERENCE NUMBER | B4: ='Data Entry'!$H$1 -> DKS/ Aasth Honda/March/2024-2025 | D4: DATE | E4: =IF('Data Entry'!$H$3<>"",'Data Entry'!$H$3,"")
A5: NAME OF SURVEYOR | B5: ='Data Entry'!$B$60 -> Dilip Kumar Sinha | D5: License Number | E5: ='Data Entry'!B66 -> 63315
A6: ='Data Entry'!A68 -> Bank Name | B6: ='Data Entry'!$B$68 -> State Bank of India | C6: ='Data Entry'!$B$69 -> Hanuman Nagar Br. | D6: ='Data Entry'!$A$70 -> IFSC Code | E6: ='Data Entry'!$B$70 -> SBIN0009005
A7: ='Data Entry'!A71 -> Bank A/c Number | B7: ='Data Entry'!$B$71 -> 20019295926 | D7: ='Data Entry'!$A$72 -> PAN Detail | E7: ='Data Entry'!$B$72 -> APZPS2395Q
A8: DATE OF SURVEY | C8: ='Data Entry'!$B$44 -> 0 | D8: License Exipry Date | E8: ='Data Entry'!$B$67 -> 46469
A9: PLACE OF SURVEY | B9: ='Data Entry'!$B$45 -> Aastha Honda Patna | D9: ALLOTMENT OF SURVEY | E9: ='Data Entry'!$B$43 -> 0
A10: INSURED NAME | B10: ='Data Entry'!$B$5 -> Mr. | D10: POLICY NUMBER | E10: ='Data Entry'!$B$4 -> 0
A11: CLAIM NUMBER | B11: ='Data Entry'!$B$3 -> 0 | D11: ASSESSED LOSS | E11: ='Data Entry'!$B$42 -> 0
A12: VEHICLE REGN. NO. | B12: ='Data Entry'!$B$18 -> 0 | D12: ESTIMATED LOSS | E12: ='Data Entry'!$B$41 -> 0
E13: =IF(c17>200000,SUM(2000+((B15-200000)*0.5%)),IF(c17>100000,1700,IF(c17>50000,1100,IF(c17>20000,900,600))))
A14: PROFESSIONAL FEE | G14: Developed by SAATH, Patna.
A15: =IF('Data Entry'!$B$41="","Survey Fee Not Payable. Please Enter Estimated Loss in Data Entry Sheet.","Survey Fee") -> Survey Fee Not Payable. Please Enter Estimated Loss in Data Entry Sheet. | E15: =IF('Data Entry'!$B$41="",0,IF(E12>200000,MIN(SUM(2800+((E12-200000)*0.7%)),12000),IF(E12>100000,2800,IF(E12>50000,1800,IF(E12>20000,1500,850))))) -> 0
A16: Spot Survey | B16: ='Data Entry'!B50 -> 0 | C16: Not Applicable | E16: =IF(OR(C16="Not Applicable",C16=""),0,IF(C16="Below 80Kms",1000,1500)) -> 0
A17: Reinspection | B17: ='Data Entry'!B51 -> 0 | C17: Not Applicable | E17: =IF(C17="Not Applicable",0,IF(C17="Below 80Kms",1000,1500)) -> 0
A19: CONVEYANCE EXPENSE
A20: ='Data Entry'!F5 -> Total No of Survey Jobs Allotted | C20: ='Data Entry'!$H$5 -> 1
A21: =IF('Data Entry'!$H$5="","Local Conveyance Not Payable. Please Enter Number of Surveys Alloted in Data Entry Sheet.","Local Conveyance") -> Local Conveyance | E21: =IF('Data Entry'!$H$5="",0,ROUND(IF('Data Entry'!$H$7="A",750,375)/'Data Entry'!$H$5,0)) -> 750
A22: Others (Specify)
A24: DAILY ALLOWANCE
A25: Not Applicable | E25: =IF(A25="Not Applicable",0,IF(A25="Half-a-day",250,500)) -> 0
A26: Not Applicable | E26: =IF(A26="Not Applicable",0,IF(A26="Half-a-day",200,400)) -> 0
A28: PHOTO CHARGES
A29: No of Final Survey Photo | C29: 10 | D29: /Photo | E29: =IF((B29*C29)>200,200,B29*C29) -> 0
A30: No of Reinsp. Photo | C30: 10 | D30: /Photo | E30: =IF(E17=0,0,IF((B30*C30)>100,100,B30*C30)) -> 0
A31: Videography | E31: 0
A33: OTHER (OUT OF POCKET) EXPENSES
A34: Courier, Postage, etc. | E34: 0
A35: Others (Specify) | E35: 0
A37: Total Amount | E37: =IF('Processing Sheet'!H59="Pls Comment abt difference","Pls comment abt diffrences in assesment sheet",SUM(E13:E36)) -> 750
A38: GST Applicable ? | D38: No | E38: =IF(D38="Yes",E37*'Data Entry'!B77,0) -> 0
A39: TOTAL (ROUNDED OFF) | E39: =ROUND(E37+E38,0) -> 750
A43: Passed For Payment
A44: Rs_______________
D47: Surveyor's Signature
A48: Competant Authority
C49: Submitted to National Insurance Company Limited

Sheet Main Survey Report
A1: ='Data Entry'!$B$60 -> Dilip Kumar Sinha | D1: ='Data Entry'!$B$61 -> V/477, Vidyapuri, Kankarbagh, Patna-800020
A2: SURVEYOR/LOSS ASSESSOR/VALUER | D2: Mobile Number | E2: ='Data Entry'!$B$63 -> 9334110636
A3: License Number | B3: ='Data Entry'!$B$66 -> 63315 | D3: Date of Expiry | E3: ='Data Entry'!$B$67 -> 46469
A4: Email Id | B4: ='Data Entry'!$B$65 -> dilipsinha11k@gmail.com | D4: Telephone Number | E4: ='Data Entry'!$B$64 -> 0
A5: PRIVATE AND CONFIDENTIAL MOTOR (FINAL) SURVEY REPORT
A7: REFERENCE NUMBER | B7: ='Data Entry'!$H$1 -> DKS/ Aasth Honda/March/2024-2025 | D7: DATE OF REPORT | E7: =IF('Data Entry'!$H$3<>"",'Data Entry'!$H$3,"")
A8: ='Data Entry'!$B$8 -> PRIVATE CAR | C8: =IF('Data Entry'!I15="Yes","Engine Protected Policy","") -> Engine Protected Policy | E8: =IF('Data Entry'!I17="No","Normal Policy","Zero Dep.Policy") -> Zero Dep.Policy
A9: This report is issued by me as licensed surveyor without prejudice, in respect of cause, nature and extent of loss/damage and subject to the terms and conditions of the insurance policy and not binding upon the liability of Insurer or the undersigned.
G10: Developed by SAATH, Patna.
A12: POLICY STATUS | E12: ='Data Entry'!G10 -> New Policy
A13: INSURER | B13: NATIONAL INSURANCE COMPANY LTD. | D13: IDV OF VEHICLE | E13: ='Data Entry'!$B$11 -> 0
A14: INSURED | B14: ='Data Entry'!$B$5 -> Mr. | D14: INSURED's PHONE NO. | E14: ='Data Entry'!B6 -> 0
A15: EMAIL ID | B15: =IF('Data Entry'!$B$7<>"",'Data Entry'!$B$7,"") | D15: POLICY NO. | E15: ='Data Entry'!$B$4 -> 0
A16: PERIOD OF INSURANCE | B16: ='Data Entry'!$B$10 -> 0 | C16: ='Data Entry'!$D$10 -> 0 | D16: ='Data Entry'!$A$3 -> CLAIM NUMBER | E16: ='Data Entry'!$B$3 -> 0
A17: FINANCER NAME | B17: =IF('Data Entry'!$B$9<>"",'Data Entry'!$B$9,"Not Appilcable") -> Not Appilcable
A19: VEHICLE DETAILS | E19: =PROPER('Data Entry'!B8) -> Private Car
A20: REGISTRATION NO. | B20: ='Data Entry'!$B$18 -> 0 | D20: REGISTRATION DATE | E20: =IF('Data Entry'!$B$19<>"",'Data Entry'!$B$19,"")
A21: CHASSIS NUMBER | B21: ='Data Entry'!$B$21 -> 0 | D21: ENGINE NUMBER | E21: ='Data Entry'!$B$22 -> 0
A22: MAKE/MODEL | B22: ='Data Entry'!$B$23 -> M/S Maruti | D22: TYPE OF BODY | E22: ='Data Entry'!$B$33 -> Saloon
A23: CUBIC CAPACITY | B23: ='Data Entry'!$B$30 -> 0 | C23: cc | D23: COLOUR OF VEHICLE | E23: ='Data Entry'!$B$24 -> 0
A24: UNLADEN WEIGHT | B24: ='Data Entry'!$B$31 -> 0 | C24: Kgs | D24: TAX PAID UPTO | E24: =IF('Data Entry'!$B$32<>"",'Data Entry'!$B$32,"") -> Road-Worthy
A25: SEATING CAPACITY | B25: ='Data Entry'!$B$35 -> 5 | C25: Persons | D25: FIR LODGED | E25: ='Data Entry'!$B$49 -> No
A26: PERMIT NUMBER | B26: =IF('Data Entry'!$B$25<>"",'Data Entry'!$B$25,"") -> NA | D26: PERMIT AUTHORISATION DETAIL | E26: =IF('Data Entry'!$B$26<>"",'Data Entry'!$B$26,"") -> NA
A27: PERMIT VALIDITY | B27: =IF('Data Entry'!$B$27<>"",'Data Entry'!$B$27,"") -> NA | C27: =IF('Data Entry'!$D$27<>"",'Data Entry'!$D$27,"") | D27: LOAD CHALLAN DETAIL | E27: =IF('Data Entry'!$B$29<>"",'Data Entry'!$B$29,"") -> NA
A28: FITNESS VALIDITY | B28: =IF('Data Entry'!$B$28<>"",'Data Entry'!$B$28,"") | C28: =IF('Data Entry'!$D$28<>"",'Data Entry'!$D$28,"") | D28: IMT ENDORSEMENT Nos. | E28: =IF('Data Entry'!$B$13<>"",'Data Entry'!$B$13,"Pls Enter Endt Nos.") -> 7,10,28,16
A30: DRIVERS DETAILS
A31: NAME OF DRIVER | B31: ='Data Entry'!$B$53 -> 0 | D31: M.D.L NUMBER | E31: ='Data Entry'!$B$54 -> 0
A32: DATE OF ISSUE | B32: =IF('Data Entry'!$B$56<>"",'Data Entry'!$B$56,"") | D32: VALID UPTO | E32: =IF('Data Entry'!$B$55<>"",'Data Entry'!$B$55,"")
A33: ISSUING AUTHORITY | B33: ='Data Entry'!$B$57 -> D.T.O Patna | D33: TYPE OF LICENSE | E33: ='Data Entry'!$B$58 -> MCWG/LMV : Light Motor Vehicle & Motor Cycle with Gear
A35: ACCIDENT AND SURVEY DETAILS
A36: DATE OF ACCIDENT | B36: =IF('Data Entry'!$B$38<>"",'Data Entry'!$B$38,"") | D36: DATE OF APPOINTMENT | E36: =IF('Data Entry'!$B$43<>"",'Data Entry'!$B$43,"")
A37: DATE OF SURVEY | B37: =IF('Data Entry'!$B$44<>"",'Data Entry'!$B$44,"") | D37: DATE OF REINSPECTION | E37: =IF('Data Entry'!$B$51<>"",'Data Entry'!$B$51,"")
A38: PLACE OF ACCIDENT | B38: ='Data Entry'!$B$39 -> 0 | D38: NO. OF CLAIM | E38: ='Data Entry'!B12 -> 1
A39: PLACE OF SURVEY | B39: ='Data Entry'!$B$45 -> Aastha Honda Patna
A41: SUMMARY OF ASSESSMENTS | D41: ASSESSED FOR
A42: TOTAL REPLACEMENT OF PARTS INCLUDING PAINT MATERIAL | D42: ='Assessment Sheet'!I180 -> 0
A43: TOTAL LABOUR CHARGES | D43: =SUM('Processing Sheet'!$H$47,'Processing Sheet'!$H$48,'Processing Sheet'!$H$50) -> 0
A44: TOWING CHARGES | D44: ='Processing Sheet'!$H$49 -> 0
A45: LESS EXCESS | D45: =SUM('Processing Sheet'!$H$54:'Processing Sheet'!$H$56) -> 1000
A46: SALVAGE VALUE(IF ANY) | D46: ='Processing Sheet'!$H$53 -> 0
A47: ROUND OFF | D47: ='Processing Sheet'!$H$57 -> 0
A48: Total Assessed Amount | D48: ='Processing Sheet'!$H$58 -> -1000
A50: CAUSE AND NATURE OF ACCIDENTS
A51: ='Data Entry'!$B$46 -> As per statement of insured and also mentioned in the claim form. While the insured vehicle was en-route. At the place of accident , . Hence the damages sustained.
A56: OBSERVATION(If any):
A57: NO
A61: DETAILS OF ASSESSMENT:-
A62: To,
A64: ='Instruction Sheet'!C22 -> Incharge
A65: ='Instruction Sheet'!C20 -> Strategic Alliance Auto Tieup Hub (Patna)
A66: National Insurance Company Ltd
A67: ='Instruction Sheet'!C23 -> "Jeewan Prakash", Fraser Road
A68: ='Instruction Sheet'!C24&"-"&'Instruction Sheet'!C26&", "&'Instruction Sheet'!C25 -> Patna-800001, Bihar
A70: Dear Sir,
A72: In accordance with valued instruction received from | D72: ='Instruction Sheet'!C21&", on "&'Data Entry'!$B$40 -> SAATH, Patna, on | E72: ='Data Entry'!$B$40 -> 0
A73: to conduct Final Survey & Assessment of loss of the above mentioned vehicle, the Undersigned collected
A74: claim papers and reached the workshop at | C74: ='Data Entry'!$B$45 -> Aastha Honda Patna
A75: The said vehicle was parked at workshop in damaged condition. The vehicle was minutely inspected and was photographed from various angles. The extent of damage was ascertained and noted. The estimate was scrutinized item wise and considering the extent of actual damages of the vehicle, a loss was arrived. The loss was discussed with the insured as well as the repairer also.
A80: My report as detailed hereunder.
A81: 1. DOCUMENTS: Related papers of the vehicle and Driving Licence verified from original(As produced).
A82: 2. T.P LOSS/ INJURY : | B82: NO
A83: 3. POLICE REPORT : | B83: NO
A84: PHYSICALLY NOTED NUMBERS -
A85: Chassis Number | B85: ='Data Entry'!$B$21 -> 0 | D85: Engine Number | E85: ='Data Entry'!$B$22 -> 0
A86: Odometer Reading | D86: Battery Number
A87: Others(If any Please specify)
A89: LIST OF DAMAGES | C89: REASON FOR REPLACEMENT | E89: PHOTO IDENTITY/ COMMENT
A90: =+'Assessment Sheet'!B81 -> 0 | C90: Damages
A91: =+'Assessment Sheet'!B82 -> 0 | C91: Damages
A92: =+'Assessment Sheet'!B83 -> 0 | C92: Damages
A93: =+'Assessment Sheet'!B84 -> 0 | C93: Damages
A94: =+'Assessment Sheet'!B85 -> 0 | C94: Damages
A95: =+'Assessment Sheet'!B86 -> 0 | C95: Damages
A96: =+'Assessment Sheet'!B87 -> 0 | C96: Damages
A97: =+'Assessment Sheet'!B88 -> 0 | C97: Damages
A98: =+'Assessment Sheet'!B89 -> 0 | C98: Damages
A99: =+'Assessment Sheet'!B90 -> 0 | C99: Damages
A100: =+'Assessment Sheet'!B91 -> 0 | C100: Damages
A101: =+'Assessment Sheet'!B92 -> 0 | C101: Damages
... A108: =+'Assessment Sheet'!B99 -> 0 | C108: Damages
A109: RECOMMENDATION:
A110: Net liability admissible is | C110: ='Processing Sheet'!$H$58 -> -1000
A113: The above damaged portions/parts were closely and carefully inspected/examined before and after dismantling of damaged parts. All technical points were taken into consideration and only consistent and allowable damages are herewith included in the final assessment (Attached herewith).
A115: This concludes my final survey & assessment report issued without prejudice, subject to the term and condition of the policy and final approval of the insurer.
D121: Surveyor's Signature
A123: Submitted to National Insurance Company Limited

Sheet Assessment Sheet
A1: LABOUR AND PARTS ASSESSMENT SHEET
A3: Name of Surveyor | C3: ='Data Entry'!$B$60 -> Dilip Kumar Sinha | F3: Date of Accident | H3: =IF('Data Entry'!$B$38<>"",'Data Entry'!$B$38,"")
A4: Policy Number | C4: ='Data Entry'!$B$4 -> 0 | F4: ='Data Entry'!$A$3 -> CLAIM NUMBER | H4: ='Data Entry'!$B$3 -> 0
A5: Insured | C5: ='Data Entry'!$B$5 -> Mr. | F5: Vehicle Reg. Number | H5: ='Data Entry'!$B$18 -> 0
A6: REFERENCE NUMBER | C6: ='Data Entry'!$H$1 -> DKS/ Aasth Honda/March/2024-2025
A7: DATE OF REPORT | C7: =IF('Data Entry'!$H$3<>"",'Data Entry'!$H$3,"")
A8: Details of Damage and Labour Assessment | J8: =IF('Data Entry'!I17="No","Normal Policy","Zero Dep.Policy") -> Zero Dep.Policy
A9: Labour Charges:
A10: Sl No. | B10: Labour Charge for Damaged Parts | D10: Job Type | E10: GST (Service) | F10: Estimated Amount | G10: Billed Amount | H10: Surveyor's Assessed Amount | I10: Final Assesment Amount | J10: GST Amount
A11: 1 | D11: R&R | E11: 0.18 | I11: =MIN(IF(F11<>"",F11,0),IF(G11<>"",G11,0),IF(H11<>"",H11,0)) -> 0 | J11: =MIN(IF(F11<>"",F11,0),IF(G11<>"",G11,0),IF(H11<>"",H11,0))*E11 -> 0
A12: 2 | D12: R&R | E12: 0.18 | I12: =MIN(IF(F12<>"",F12,0),IF(G12<>"",G12,0),IF(H12<>"",H12,0)) -> 0 | J12: =MIN(IF(F12<>"",F12,0),IF(G12<>"",G12,0),IF(H12<>"",H12,0))*E12 -> 0 | L12: Developed by SAATH, Patna.
A13: 3 | D13: Repair/Dent | E13: 0.18 | I13: =MIN(IF(F13<>"",F13,0),IF(G13<>"",G13,0),IF(H13<>"",H13,0)) -> 0 | J13: =MIN(IF(F13<>"",F13,0),IF(G13<>"",G13,0),IF(H13<>"",H13,0))*E13 -> 0
A14: 4 | I14: =MIN(IF(F14<>"",F14,0),IF(G14<>"",G14,0),IF(H14<>"",H14,0)) -> 0 | J14: =MIN(IF(F14<>"",F14,0),IF(G14<>"",G14,0),IF(H14<>"",H14,0))*E14 -> 0
A15: 5 | I15: =MIN(IF(F15<>"",F15,0),IF(G15<>"",G15,0),IF(H15<>"",H15,0)) -> 0 | J15: =MIN(IF(F15<>"",F15,0),IF(G15<>"",G15,0),IF(H15<>"",H15,0))*E15 -> 0
A16: 6 | I16: =MIN(IF(F16<>"",F16,0),IF(G16<>"",G16,0),IF(H16<>"",H16,0)) -> 0 | J16: =MIN(IF(F16<>"",F16,0),IF(G16<>"",G16,0),IF(H16<>"",H16,0))*E16 -> 0
A17: 7 | I17: =MIN(IF(F17<>"",F17,0),IF(G17<>"",G17,0),IF(H17<>"",H17,0)) -> 0 | J17: =MIN(IF(F17<>"",F17,0),IF(G17<>"",G17,0),IF(H17<>"",H17,0))*E17 -> 0
A18: 8 | I18: =MIN(IF(F18<>"",F18,0),IF(G18<>"",G18,0),IF(H18<>"",H18,0)) -> 0 | J18: =MIN(IF(F18<>"",F18,0),IF(G18<>"",G18,0),IF(H18<>"",H18,0))*E18 -> 0
A19: 9 | I19: =MIN(IF(F19<>"",F19,0),IF(G19<>"",G19,0),IF(H19<>"",H19,0)) -> 0 | J19: =MIN(IF(F19<>"",F19,0),IF(G19<>"",G19,0),IF(H19<>"",H19,0))*E19 -> 0
A20: 10 | I20: =MIN(IF(F20<>"",F20,0),IF(G20<>"",G20,0),IF(H20<>"",H20,0)) -> 0 | J20: =MIN(IF(F20<>"",F20,0),IF(G20<>"",G20,0),IF(H20<>"",H20,0))*E20 -> 0
A21: 11 | I21: =MIN(IF(F21<>"",F21,0),IF(G21<>"",G21,0),IF(H21<>"",H21,0)) -> 0 | J21: =MIN(IF(F21<>"",F21,0),IF(G21<>"",G21,0),IF(H21<>"",H21,0))*E21 -> 0
A22: 12 | I22: =MIN(IF(F22<>"",F22,0),IF(G22<>"",G22,0),IF(H22<>"",H22,0)) -> 0 | J22: =MIN(IF(F22<>"",F22,0),IF(G22<>"",G22,0),IF(H22<>"",H22,0))*E22 -> 0
A23: 13 | I23: =MIN(IF(F23<>"",F23,0),IF(G23<>"",G23,0),IF(H23<>"",H23,0)) -> 0 | J23: =MIN(IF(F23<>"",F23,0),IF(G23<>"",G23,0),IF(H23<>"",H23,0))*E23 -> 0
A24: 14 | I24: =MIN(IF(F24<>"",F24,0),IF(G24<>"",G24,0),IF(H24<>"",H24,0)) -> 0 | J24: =MIN(IF(F24<>"",F24,0),IF(G24<>"",G24,0),IF(H24<>"",H24,0))*E24 -> 0
A25: 15 | I25: =MIN(IF(F25<>"",F25,0),IF(G25<>"",G25,0),IF(H25<>"",H25,0)) -> 0 | J25: =MIN(IF(F25<>"",F25,0),IF(G25<>"",G25,0),IF(H25<>"",H25,0))*E25 -> 0
... A40: 30 | I40: =MIN(IF(F40<>"",F40,0),IF(G40<>"",G40,0),IF(H40<>"",H40,0)) -> 0 | J40: =MIN(IF(F40<>"",F40,0),IF(G40<>"",G40,0),IF(H40<>"",H40,0))*E40 -> 0
A41: Total Amount | F41: =SUM(F11:F40) -> 0 | G41: =SUM(G11:G40) -> 0 | H41: =SUM(H11:H40) -> 0 | I41: =SUM(I11:I40) -> 0 | J41: =SUM(J11:J40) -> 0
A43: Labour Charges For Painting Only :
A44: Sl No. | B44: List of Damaged Parts | D44: Job Type | E44: GST (Service) | F44: Estimated Amount | G44: Billed Amount | H44: Surveyor's Assessed Amount | I44: Final Assesment Amount | J44: GST Amount
A45: 1 | D45: Painting | E45: ='Data Entry'!$B$77 -> 0.18 | I45: =MIN(IF(F45<>"",F45,0),IF(G45<>"",G45,0),IF(H45<>"",H45,0)) -> 0 | J45: =MIN(IF(F45<>"",F45,0),IF(G45<>"",G45,0),IF(H45<>"",H45,0))*E45 -> 0
A46: 2 | D46: Painting | E46: ='Data Entry'!$B$77 -> 0.18 | I46: =MIN(IF(F46<>"",F46,0),IF(G46<>"",G46,0),IF(H46<>"",H46,0)) -> 0 | J46: =MIN(IF(F46<>"",F46,0),IF(G46<>"",G46,0),IF(H46<>"",H46,0))*E46 -> 0
A47: 3 | D47: Painting | E47: ='Data Entry'!$B$77 -> 0.18 | I47: =MIN(IF(F47<>"",F47,0),IF(G47<>"",G47,0),IF(H47<>"",H47,0)) -> 0 | J47: =MIN(IF(F47<>"",F47,0),IF(G47<>"",G47,0),IF(H47<>"",H47,0))*E47 -> 0
A48: 4 | D48: Painting | I48: =MIN(IF(F48<>"",F48,0),IF(G48<>"",G48,0),IF(H48<>"",H48,0)) -> 0 | J48: =MIN(IF(F48<>"",F48,0),IF(G48<>"",G48,0),IF(H48<>"",H48,0))*E48 -> 0
A49: 5 | D49: Painting | I49: =MIN(IF(F49<>"",F49,0),IF(G49<>"",G49,0),IF(H49<>"",H49,0)) -> 0 | J49: =MIN(IF(F49<>"",F49,0),IF(G49<>"",G49,0),IF(H49<>"",H49,0))*E49 -> 0
A50: 6 | D50: Painting | I50: =MIN(IF(F50<>"",F50,0),IF(G50<>"",G50,0),IF(H50<>"",H50,0)) -> 0 | J50: =MIN(IF(F50<>"",F50,0),IF(G50<>"",G50,0),IF(H50<>"",H50,0))*E50 -> 0
A51: 7 | D51: Painting | I51: =MIN(IF(F51<>"",F51,0),IF(G51<>"",G51,0),IF(H51<>"",H51,0)) -> 0 | J51: =MIN(IF(F51<>"",F51,0),IF(G51<>"",G51,0),IF(H51<>"",H51,0))*E51 -> 0
A52: 8 | D52: Painting | I52: =MIN(IF(F52<>"",F52,0),IF(G52<>"",G52,0),IF(H52<>"",H52,0)) -> 0 | J52: =MIN(IF(F52<>"",F52,0),IF(G52<>"",G52,0),IF(H52<>"",H52,0))*E52 -> 0
A53: 9 | D53: Painting | I53: =MIN(IF(F53<>"",F53,0),IF(G53<>"",G53,0),IF(H53<>"",H53,0)) -> 0 | J53: =MIN(IF(F53<>"",F53,0),IF(G53<>"",G53,0),IF(H53<>"",H53,0))*E53 -> 0
A54: 10 | D54: Painting | I54: =MIN(IF(F54<>"",F54,0),IF(G54<>"",G54,0),IF(H54<>"",H54,0)) -> 0 | J54: =MIN(IF(F54<>"",F54,0),IF(G54<>"",G54,0),IF(H54<>"",H54,0))*E54 -> 0
A55: 11 | D55: Painting | I55: =MIN(IF(F55<>"",F55,0),IF(G55<>"",G55,0),IF(H55<>"",H55,0)) -> 0 | J55: =MIN(IF(F55<>"",F55,0),IF(G55<>"",G55,0),IF(H55<>"",H55,0))*E55 -> 0
A56: 12 | D56: Painting | I56: =MIN(IF(F56<>"",F56,0),IF(G56<>"",G56,0),IF(H56<>"",H56,0)) -> 0 | J56: =MIN(IF(F56<>"",F56,0),IF(G56<>"",G56,0),IF(H56<>"",H56,0))*E56 -> 0
A57: 13 | D57: Painting | I57: =MIN(IF(F57<>"",F57,0),IF(G57<>"",G57,0),IF(H57<>"",H57,0)) -> 0 | J57: =MIN(IF(F57<>"",F57,0),IF(G57<>"",G57,0),IF(H57<>"",H57,0))*E57 -> 0
A58: 14 | D58: Painting | I58: =MIN(IF(F58<>"",F58,0),IF(G58<>"",G58,0),IF(H58<>"",H58,0)) -> 0 | J58: =MIN(IF(F58<>"",F58,0),IF(G58<>"",G58,0),IF(H58<>"",H58,0))*E58 -> 0
A59: 15 | D59: Painting | I59: =MIN(IF(F59<>"",F59,0),IF(G59<>"",G59,0),IF(H59<>"",H59,0)) -> 0 | J59: =MIN(IF(F59<>"",F59,0),IF(G59<>"",G59,0),IF(H59<>"",H59,0))*E59 -> 0
... A69: 25 | D69: Painting | I69: =MIN(IF(F69<>"",F69,0),IF(G69<>"",G69,0),IF(H69<>"",H69,0)) -> 0 | J69: =MIN(IF(F69<>"",F69,0),IF(G69<>"",G69,0),IF(H69<>"",H69,0))*E69 -> 0
A70: Total Amount | F70: =SUM(F45:F69) -> 0 | G70: =SUM(G45:G69) -> 0 | H70: =SUM(H45:H69) -> 0 | I70: =SUM(I45:I69) -> 0 | J70: =SUM(J45:J69) -> 0
A71: Whether Painting charged on Lumpsum basis? | G71: No
A72: =IF(G71="Yes","Total Painting Labour Charge Allowed after depreciation (75%)","Total Painting Labour Charge Allowed") -> Total Painting Labour Charge Allowed | G72: =IF(G71="Yes",(0.75*(I70)),(I70)) -> 0
A73: GST Applicable on Painting Labour Charge | G73: =IF(G71="Yes",(0.75*J70),J70) -> 0
A74: Paint Material Cost applicable for depreciation | G74: =IF(G71="Yes",(0.25*(I70)),0) -> 0
A77: Replacement of Parts :
A78: SL NO | B78: NAME OF PARTS | C78: MATERIAL OF PARTS | D78: GST (Parts) | E78: ESTIMATED COST | F78: BILLED AMOUNT | G78: SURVEYOR'S ASSESSED AMOUNT | H78: Dep % | I78: FINAL ASSESMENT | J78: FINALGST
A79: 1 | B79: =IF(G71="No","Not Applicable","Cost of Paint Material (25% of Lumpsum Painting Labur Charge)") -> Not Applicable | C79: PAINT (Lablour) | D79: ='Data Entry'!B77 -> 0.18 | E79: Not Applicable | G79: ='Assessment Sheet'!$G$74 -> 0 | H79: =IF('Data Entry'!I17="Yes",0,50) -> 0 | I79: =G79-G79*H79/100 -> 0 | J79: =I79*D79 -> 0 | K79: This part automatically comes when Labour charge is only charged. Only we need to select Depreciation is applicable in Labour Assessment Sheet.
A80: 2 | B80: =IF(G71="Yes","Not Applicable","Cost of Paint Material (Calculated on a segregated basis Parts)") -> Cost of Paint Material (Calculated on a segregated basis Parts) | C80: PAINT | D80: 0.18 | E80: Not Applicable | H80: =IF('Data Entry'!I17="Yes",0,50) -> 0 | I80: =IF(I79<=0,(G80-G80*H80/100),0) -> 0 | J80: =I80*D80 -> 0 | K80: Please note that this part should be only used when Cost of Paint material is provided separately in Bill.
A81: 3 | C81: PLASTIC | D81: 0.18 | H81: =IF(C81="",0,IF('Data Entry'!$I$17="Yes",0,VLOOKUP(C81,'Data Entry'!$F$65:$G$71,2,FALSE))) -> 0 | I81: =IF(C81="",0,MIN(IF(E81<>"",E81,0),IF(F81<>"",F81,0),IF(G81<"",G81,0))-(H81*MIN(IF(E81<>"",E81,0),IF(F81<>"",F81,0),IF(G81<"",G81,0))/100)) -> 0 | J81: =I81*D81 -> 0
A82: 4 | C82: PLASTIC | D82: 0.18 | H82: =IF(C82="",0,IF('Data Entry'!$I$17="Yes",0,VLOOKUP(C82,'Data Entry'!$F$65:$G$71,2,FALSE))) -> 0 | I82: =IF(C82="",0,MIN(IF(E82<>"",E82,0),IF(F82<>"",F82,0),IF(G82<"",G82,0))-(H82*MIN(IF(E82<>"",E82,0),IF(F82<>"",F82,0),IF(G82<"",G82,0))/100)) -> 0 | J82: =I82*D82 -> 0
A83: 5 | C83: PLASTIC | D83: 0.18 | H83: =IF(C83="",0,IF('Data Entry'!$I$17="Yes",0,VLOOKUP(C83,'Data Entry'!$F$65:$G$71,2,FALSE))) -> 0 | I83: =IF(C83="",0,MIN(IF(E83<>"",E83,0),IF(F83<>"",F83,0),IF(G83<"",G83,0))-(H83*MIN(IF(E83<>"",E83,0),IF(F83<>"",F83,0),IF(G83<"",G83,0))/100)) -> 0 | J83: =I83*D83 -> 0
A84: 6 | C84: PLASTIC | D84: 0.18 | H84: =IF(C84="",0,IF('Data Entry'!$I$17="Yes",0,VLOOKUP(C84,'Data Entry'!$F$65:$G$71,2,FALSE))) -> 0 | I84: =IF(C84="",0,MIN(IF(E84<>"",E84,0),IF(F84<>"",F84,0),IF(G84<"",G84,0))-(H84*MIN(IF(E84<>"",E84,0),IF(F84<>"",F84,0),IF(G84<"",G84,0))/100)) -> 0 | J84: =I84*D84 -> 0
A85: 7 | C85: GLASS | D85: 0.18 | H85: =IF(C85="",0,IF('Data Entry'!$I$17="Yes",0,VLOOKUP(C85,'Data Entry'!$F$65:$G$71,2,FALSE))) -> 0 | I85: =IF(C85="",0,MIN(IF(E85<>"",E85,0),IF(F85<>"",F85,0),IF(G85<"",G85,0))-(H85*MIN(IF(E85<>"",E85,0),IF(F85<>"",F85,0),IF(G85<"",G85,0))/100)) -> 0 | J85: =I85*D85 -> 0
A86: 8 | C86: PLASTIC | D86: 0.18 | H86: =IF(C86="",0,IF('Data Entry'!$I$17="Yes",0,VLOOKUP(C86,'Data Entry'!$F$65:$G$71,2,FALSE))) -> 0 | I86: =IF(C86="",0,MIN(IF(E86<>"",E86,0),IF(F86<>"",F86,0),IF(G86<"",G86,0))-(H86*MIN(IF(E86<>"",E86,0),IF(F86<>"",F86,0),IF(G86<"",G86,0))/100)) -> 0 | J86: =I86*D86 -> 0
A87: 9 | H87: =IF(C87="",0,IF('Data Entry'!$I$17="Yes",0,VLOOKUP(C87,'Data Entry'!$F$65:$G$71,2,FALSE))) -> 0 | I87: =IF(C87="",0,MIN(IF(E87<>"",E87,0),IF(F87<>"",F87,0),IF(G87<"",G87,0))-(H87*MIN(IF(E87<>"",E87,0),IF(F87<>"",F87,0),IF(G87<"",G87,0))/100)) -> 0 | J87: =I87*D87 -> 0
A88: 10 | H88: =IF(C88="",0,IF('Data Entry'!$I$17="Yes",0,VLOOKUP(C88,'Data Entry'!$F$65:$G$71,2,FALSE))) -> 0 | I88: =IF(C88="",0,MIN(IF(E88<>"",E88,0),IF(F88<>"",F88,0),IF(G88<"",G88,0))-(H88*MIN(IF(E88<>"",E88,0),IF(F88<>"",F88,0),IF(G88<"",G88,0))/100)) -> 0 | J88: =I88*D88 -> 0
A89: 11 | H89: =IF(C89="",0,IF('Data Entry'!$I$17="Yes",0,VLOOKUP(C89,'Data Entry'!$F$65:$G$71,2,FALSE))) -> 0 | I89: =IF(C89="",0,MIN(IF(E89<>"",E89,0),IF(F89<>"",F89,0),IF(G89<"",G89,0))-(H89*MIN(IF(E89<>"",E89,0),IF(F89<>"",F89,0),IF(G89<"",G89,0))/100)) -> 0 | J89: =I89*D89 -> 0
A90: 12 | H90: =IF(C90="",0,IF('Data Entry'!$I$17="Yes",0,VLOOKUP(C90,'Data Entry'!$F$65:$G$71,2,FALSE))) -> 0 | I90: =IF(C90="",0,MIN(IF(E90<>"",E90,0),IF(F90<>"",F90,0),IF(G90<"",G90,0))-(H90*MIN(IF(E90<>"",E90,0),IF(F90<>"",F90,0),IF(G90<"",G90,0))/100)) -> 0 | J90: =I90*D90 -> 0
A91: 13 | H91: =IF(C91="",0,IF('Data Entry'!$I$17="Yes",0,VLOOKUP(C91,'Data Entry'!$F$65:$G$71,2,FALSE))) -> 0 | I91: =IF(C91="",0,MIN(IF(E91<>"",E91,0),IF(F91<>"",F91,0),IF(G91<"",G91,0))-(H91*MIN(IF(E91<>"",E91,0),IF(F91<>"",F91,0),IF(G91<"",G91,0))/100)) -> 0 | J91: =I91*D91 -> 0
A92: 14 | H92: =IF(C92="",0,IF('Data Entry'!$I$17="Yes",0,VLOOKUP(C92,'Data Entry'!$F$65:$G$71,2,FALSE))) -> 0 | I92: =IF(C92="",0,MIN(IF(E92<>"",E92,0),IF(F92<>"",F92,0),IF(G92<"",G92,0))-(H92*MIN(IF(E92<>"",E92,0),IF(F92<>"",F92,0),IF(G92<"",G92,0))/100)) -> 0 | J92: =I92*D92 -> 0
A93: 15 | H93: =IF(C93="",0,IF('Data Entry'!$I$17="Yes",0,VLOOKUP(C93,'Data Entry'!$F$65:$G$71,2,FALSE))) -> 0 | I93: =IF(C93="",0,MIN(IF(E93<>"",E93,0),IF(F93<>"",F93,0),IF(G93<"",G93,0))-(H93*MIN(IF(E93<>"",E93,0),IF(F93<>"",F93,0),IF(G93<"",G93,0))/100)) -> 0 | J93: =I93*D93 -> 0
A94: 16 | H94: =IF(C94="",0,IF('Data Entry'!$I$17="Yes",0,VLOOKUP(C94,'Data Entry'!$F$65:$G$71,2,FALSE))) -> 0 | I94: =IF(C94="",0,MIN(IF(E94<>"",E94,0),IF(F94<>"",F94,0),IF(G94<"",G94,0))-(H94*MIN(IF(E94<>"",E94,0),IF(F94<>"",F94,0),IF(G94<"",G94,0))/100)) -> 0 | J94: =I94*D94 -> 0
A95: 17 | H95: =IF(C95="",0,IF('Data Entry'!$I$17="Yes",0,VLOOKUP(C95,'Data Entry'!$F$65:$G$71,2,FALSE))) -> 0 | I95: =IF(C95="",0,MIN(IF(E95<>"",E95,0),IF(F95<>"",F95,0),IF(G95<"",G95,0))-(H95*MIN(IF(E95<>"",E95,0),IF(F95<>"",F95,0),IF(G95<"",G95,0))/100)) -> 0 | J95: =I95*D95 -> 0
A96: 18 | H96: =IF(C96="",0,IF('Data Entry'!$I$17="Yes",0,VLOOKUP(C96,'Data Entry'!$F$65:$G$71,2,FALSE))) -> 0 | I96: =IF(C96="",0,MIN(IF(E96<>"",E96,0),IF(F96<>"",F96,0),IF(G96<"",G96,0))-(H96*MIN(IF(E96<>"",E96,0),IF(F96<>"",F96,0),IF(G96<"",G96,0))/100)) -> 0 | J96: =I96*D96 -> 0
A97: 19 | H97: =IF(C97="",0,IF('Data Entry'!$I$17="Yes",0,VLOOKUP(C97,'Data Entry'!$F$65:$G$71,2,FALSE))) -> 0 | I97: =IF(C97="",0,MIN(IF(E97<>"",E97,0),IF(F97<>"",F97,0),IF(G97<"",G97,0))-(H97*MIN(IF(E97<>"",E97,0),IF(F97<>"",F97,0),IF(G97<"",G97,0))/100)) -> 0 | J97: =I97*D97 -> 0
A98: 20 | H98: =IF(C98="",0,IF('Data Entry'!$I$17="Yes",0,VLOOKUP(C98,'Data Entry'!$F$65:$G$71,2,FALSE))) -> 0 | I98: =IF(C98="",0,MIN(IF(E98<>"",E98,0),IF(F98<>"",F98,0),IF(G98<"",G98,0))-(H98*MIN(IF(E98<>"",E98,0),IF(F98<>"",F98,0),IF(G98<"",G98,0))/100)) -> 0 | J98: =I98*D98 -> 0
A99: 21 | C99: PLASTIC | D99: 0.28 | G99: =F99 -> 0 | H99: =IF(C99="",0,IF('Data Entry'!$I$17="Yes",0,VLOOKUP(C99,'Data Entry'!$F$65:$G$71,2,FALSE))) -> 0 | I99: =IF(C99="",0,MIN(IF(E99<>"",E99,0),IF(F99<>"",F99,0),IF(G99<"",G99,0))-(H99*MIN(IF(E99<>"",E99,0),IF(F99<>"",F99,0),IF(G99<"",G99,0))/100)) -> 0 | J99: =I99*D99 -> 0
A100: 22 | C100: PLASTIC | D100: 0.28 | G100: =F100 -> 0 | H100: =IF(C100="",0,IF('Data Entry'!$I$17="Yes",0,VLOOKUP(C100,'Data Entry'!$F$65:$G$71,2,FALSE))) -> 0 | I100: =IF(C100="",0,MIN(IF(E100<>"",E100,0),IF(F100<>"",F100,0),IF(G100<"",G100,0))-(H100*MIN(IF(E100<>"",E100,0),IF(F100<>"",F100,0),IF(G100<"",G100,0))/100)) -> 0 | J100: =I100*D100 -> 0
A101: 23 | C101: PLASTIC | D101: 0.28 | G101: =F101 -> 0 | H101: =IF(C101="",0,IF('Data Entry'!$I$17="Yes",0,VLOOKUP(C101,'Data Entry'!$F$65:$G$71,2,FALSE))) -> 0 | I101: =IF(C101="",0,MIN(IF(E101<>"",E101,0),IF(F101<>"",F101,0),IF(G101<"",G101,0))-(H101*MIN(IF(E101<>"",E101,0),IF(F101<>"",F101,0),IF(G101<"",G101,0))/100)) -> 0 | J101: =I101*D101 -> 0
A102: 24 | C102: PLASTIC | D102: 0.28 | G102: =F102 -> 0 | H102: =IF(C102="",0,IF('Data Entry'!$I$17="Yes",0,VLOOKUP(C102,'Data Entry'!$F$65:$G$71,2,FALSE))) -> 0 | I102: =IF(C102="",0,MIN(IF(E102<>"",E102,0),IF(F102<>"",F102,0),IF(G102<"",G102,0))-(H102*MIN(IF(E102<>"",E102,0),IF(F102<>"",F102,0),IF(G102<"",G102,0))/100)) -> 0 | J102: =I102*D102 -> 0
A103: 25 | C103: PLASTIC | D103: 0.28 | G103: =F103 -> 0 | H103: =IF(C103="",0,IF('Data Entry'!$I$17="Yes",0,VLOOKUP(C103,'Data Entry'!$F$65:$G$71,2,FALSE))) -> 0 | I103: =IF(C103="",0,MIN(IF(E103<>"",E103,0),IF(F103<>"",F103,0),IF(G103<"",G103,0))-(H103*MIN(IF(E103<>"",E103,0),IF(F103<>"",F103,0),IF(G103<"",G103,0))/100)) -> 0 | J103: =I103*D103 -> 0
A104: 26 | C104: PLASTIC | D104: 0.28 | G104: =F104 -> 0 | H104: =IF(C104="",0,IF('Data Entry'!$I$17="Yes",0,VLOOKUP(C104,'Data Entry'!$F$65:$G$71,2,FALSE))) -> 0 | I104: =IF(C104="",0,MIN(IF(E104<>"",E104,0),IF(F104<>"",F104,0),IF(G104<"",G104,0))-(H104*MIN(IF(E104<>"",E104,0),IF(F104<>"",F104,0),IF(G104<"",G104,0))/100)) -> 0 | J104: =I104*D104 -> 0
A105: 27 | C105: PLASTIC | D105: 0.28 | G105: =F105 -> 0 | H105: =IF(C105="",0,IF('Data Entry'!$I$17="Yes",0,VLOOKUP(C105,'Data Entry'!$F$65:$G$71,2,FALSE))) -> 0 | I105: =IF(C105="",0,MIN(IF(E105<>"",E105,0),IF(F105<>"",F105,0),IF(G105<"",G105,0))-(H105*MIN(IF(E105<>"",E105,0),IF(F105<>"",F105,0),IF(G105<"",G105,0))/100)) -> 0 | J105: =I105*D105 -> 0
A106: 28 | C106: PLASTIC | D106: 0.28 | G106: =F106 -> 0 | H106: =IF(C106="",0,IF('Data Entry'!$I$17="Yes",0,VLOOKUP(C106,'Data Entry'!$F$65:$G$71,2,FALSE))) -> 0 | I106: =IF(C106="",0,MIN(IF(E106<>"",E106,0),IF(F106<>"",F106,0),IF(G106<"",G106,0))-(H106*MIN(IF(E106<>"",E106,0),IF(F106<>"",F106,0),IF(G106<"",G106,0))/100)) -> 0 | J106: =I106*D106 -> 0
A107: 29 | C107: PLASTIC | D107: 0.28 | G107: =F107 -> 0 | H107: =IF(C107="",0,IF('Data Entry'!$I$17="Yes",0,VLOOKUP(C107,'Data Entry'!$F$65:$G$71,2,FALSE))) -> 0 | I107: =IF(C107="",0,MIN(IF(E107<>"",E107,0),IF(F107<>"",F107,0),IF(G107<"",G107,0))-(H107*MIN(IF(E107<>"",E107,0),IF(F107<>"",F107,0),IF(G107<"",G107,0))/100)) -> 0 | J107: =I107*D107 -> 0
A108: 30 | C108: PLASTIC | D108: 0.28 | G108: =F108 -> 0 | H108: =IF(C108="",0,IF('Data Entry'!$I$17="Yes",0,VLOOKUP(C108,'Data Entry'!$F$65:$G$71,2,FALSE))) -> 0 | I108: =IF(C108="",0,MIN(IF(E108<>"",E108,0),IF(F108<>"",F108,0),IF(G108<"",G108,0))-(H108*MIN(IF(E108<>"",E108,0),IF(F108<>"",F108,0),IF(G108<"",G108,0))/100)) -> 0 | J108: =I108*D108 -> 0
A109: 31 | C109: PLASTIC | D109: 0.28 | G109: =F109 -> 0 | H109: =IF(C109="",0,IF('Data Entry'!$I$17="Yes",0,VLOOKUP(C109,'Data Entry'!$F$65:$G$71,2,FALSE))) -> 0 | I109: =IF(C109="",0,MIN(IF(E109<>"",E109,0),IF(F109<>"",F109,0),IF(G109<"",G109,0))-(H109*MIN(IF(E109<>"",E109,0),IF(F109<>"",F109,0),IF(G109<"",G109,0))/100)) -> 0 | J109: =I109*D109 -> 0
A110: 32 | C110: PLASTIC | D110: 0.28 | G110: =F110 -> 0 | H110: =IF(C110="",0,IF('Data Entry'!$I$17="Yes",0,VLOOKUP(C110,'Data Entry'!$F$65:$G$71,2,FALSE))) -> 0 | I110: =IF(C110="",0,MIN(IF(E110<>"",E110,0),IF(F110<>"",F110,0),IF(G110<"",G110,0))-(H110*MIN(IF(E110<>"",E110,0),IF(F110<>"",F110,0),IF(G110<"",G110,0))/100)) -> 0 | J110: =I110*D110 -> 0
... A141: 63 | C141: PLASTIC | D141: 0.28 | G141: =F141 -> 0 | H141: =IF(C141="",0,IF('Data Entry'!$I$17="Yes",0,VLOOKUP(C141,'Data Entry'!$F$65:$G$71,2,FALSE))) -> 0 | I141: =IF(C141="",0,MIN(IF(E141<>"",E141,0),IF(F141<>"",F141,0),IF(G141<"",G141,0))-(H141*MIN(IF(E141<>"",E141,0),IF(F141<>"",F141,0),IF(G141<"",G141,0))/100)) -> 0 | J141: =I141*D141 -> 0
A142: 64 | G142: =F142 -> 0 | H142: =IF(C142="",0,IF('Data Entry'!$I$17="Yes",0,VLOOKUP(C142,'Data Entry'!$F$65:$G$71,2,FALSE))) -> 0 | I142: =IF(C142="",0,MIN(IF(E142<>"",E142,0),IF(F142<>"",F142,0),IF(G142<"",G142,0))-(H142*MIN(IF(E142<>"",E142,0),IF(F142<>"",F142,0),IF(G142<"",G142,0))/100)) -> 0 | J142: =I142*D142 -> 0
A143: 65 | G143: =F143 -> 0 | H143: =IF(C143="",0,IF('Data Entry'!$I$17="Yes",0,VLOOKUP(C143,'Data Entry'!$F$65:$G$71,2,FALSE))) -> 0 | I143: =IF(C143="",0,MIN(IF(E143<>"",E143,0),IF(F143<>"",F143,0),IF(G143<"",G143,0))-(H143*MIN(IF(E143<>"",E143,0),IF(F143<>"",F143,0),IF(G143<"",G143,0))/100)) -> 0 | J143: =I143*D143 -> 0
A144: 66 | G144: =F144 -> 0 | H144: =IF(C144="",0,IF('Data Entry'!$I$17="Yes",0,VLOOKUP(C144,'Data Entry'!$F$65:$G$71,2,FALSE))) -> 0 | I144: =IF(C144="",0,MIN(IF(E144<>"",E144,0),IF(F144<>"",F144,0),IF(G144<"",G144,0))-(H144*MIN(IF(E144<>"",E144,0),IF(F144<>"",F144,0),IF(G144<"",G144,0))/100)) -> 0 | J144: =I144*D144 -> 0
A145: 67 | G145: =F145 -> 0 | H145: =IF(C145="",0,IF('Data Entry'!$I$17="Yes",0,VLOOKUP(C145,'Data Entry'!$F$65:$G$71,2,FALSE))) -> 0 | I145: =IF(C145="",0,MIN(IF(E145<>"",E145,0),IF(F145<>"",F145,0),IF(G145<"",G145,0))-(H145*MIN(IF(E145<>"",E145,0),IF(F145<>"",F145,0),IF(G145<"",G145,0))/100)) -> 0 | J145: =I145*D145 -> 0
A146: 68 | G146: =F146 -> 0 | H146: =IF(C146="",0,IF('Data Entry'!$I$17="Yes",0,VLOOKUP(C146,'Data Entry'!$F$65:$G$71,2,FALSE))) -> 0 | I146: =IF(C146="",0,MIN(IF(E146<>"",E146,0),IF(F146<>"",F146,0),IF(G146<"",G146,0))-(H146*MIN(IF(E146<>"",E146,0),IF(F146<>"",F146,0),IF(G146<"",G146,0))/100)) -> 0 | J146: =I146*D146 -> 0
A147: 69 | G147: =F147 -> 0 | H147: =IF(C147="",0,IF('Data Entry'!$I$17="Yes",0,VLOOKUP(C147,'Data Entry'!$F$65:$G$71,2,FALSE))) -> 0 | I147: =IF(C147="",0,MIN(IF(E147<>"",E147,0),IF(F147<>"",F147,0),IF(G147<"",G147,0))-(H147*MIN(IF(E147<>"",E147,0),IF(F147<>"",F147,0),IF(G147<"",G147,0))/100)) -> 0 | J147: =I147*D147 -> 0
A148: 70 | G148: =F148 -> 0 | H148: =IF(C148="",0,IF('Data Entry'!$I$17="Yes",0,VLOOKUP(C148,'Data Entry'!$F$65:$G$71,2,FALSE))) -> 0 | I148: =IF(C148="",0,MIN(IF(E148<>"",E148,0),IF(F148<>"",F148,0),IF(G148<"",G148,0))-(H148*MIN(IF(E148<>"",E148,0),IF(F148<>"",F148,0),IF(G148<"",G148,0))/100)) -> 0 | J148: =I148*D148 -> 0
A149: 71 | G149: =F149 -> 0 | H149: =IF(C149="",0,IF('Data Entry'!$I$17="Yes",0,VLOOKUP(C149,'Data Entry'!$F$65:$G$71,2,FALSE))) -> 0 | I149: =IF(C149="",0,MIN(IF(E149<>"",E149,0),IF(F149<>"",F149,0),IF(G149<"",G149,0))-(H149*MIN(IF(E149<>"",E149,0),IF(F149<>"",F149,0),IF(G149<"",G149,0))/100)) -> 0 | J149: =I149*D149 -> 0
A150: 72 | G150: =F150 -> 0 | H150: =IF(C150="",0,IF('Data Entry'!$I$17="Yes",0,VLOOKUP(C150,'Data Entry'!$F$65:$G$71,2,FALSE))) -> 0 | I150: =IF(C150="",0,MIN(IF(E150<>"",E150,0),IF(F150<>"",F150,0),IF(G150<"",G150,0))-(H150*MIN(IF(E150<>"",E150,0),IF(F150<>"",F150,0),IF(G150<"",G150,0))/100)) -> 0 | J150: =I150*D150 -> 0
A151: 73 | G151: =F151 -> 0 | H151: =IF(C151="",0,IF('Data Entry'!$I$17="Yes",0,VLOOKUP(C151,'Data Entry'!$F$65:$G$71,2,FALSE))) -> 0 | I151: =IF(C151="",0,MIN(IF(E151<>"",E151,0),IF(F151<>"",F151,0),IF(G151<"",G151,0))-(H151*MIN(IF(E151<>"",E151,0),IF(F151<>"",F151,0),IF(G151<"",G151,0))/100)) -> 0 | J151: =I151*D151 -> 0
A152: 74 | G152: =F152 -> 0 | H152: =IF(C152="",0,IF('Data Entry'!$I$17="Yes",0,VLOOKUP(C152,'Data Entry'!$F$65:$G$71,2,FALSE))) -> 0 | I152: =IF(C152="",0,MIN(IF(E152<>"",E152,0),IF(F152<>"",F152,0),IF(G152<"",G152,0))-(H152*MIN(IF(E152<>"",E152,0),IF(F152<>"",F152,0),IF(G152<"",G152,0))/100)) -> 0 | J152: =I152*D152 -> 0
A153: 75 | G153: =F153 -> 0 | H153: =IF(C153="",0,IF('Data Entry'!$I$17="Yes",0,VLOOKUP(C153,'Data Entry'!$F$65:$G$71,2,FALSE))) -> 0 | I153: =IF(C153="",0,MIN(IF(E153<>"",E153,0),IF(F153<>"",F153,0),IF(G153<"",G153,0))-(H153*MIN(IF(E153<>"",E153,0),IF(F153<>"",F153,0),IF(G153<"",G153,0))/100)) -> 0 | J153: =I153*D153 -> 0
... A178: 100 | G178: =F178 -> 0 | H178: =IF(C178="",0,IF('Data Entry'!$I$17="Yes",0,VLOOKUP(C178,'Data Entry'!$F$65:$G$71,2,FALSE))) -> 0 | I178: =IF(C178="",0,MIN(IF(E178<>"",E178,0),IF(F178<>"",F178,0),IF(G178<"",G178,0))-(H178*MIN(IF(E178<>"",E178,0),IF(F178<>"",F178,0),IF(G178<"",G178,0))/100)) -> 0 | J178: =I178*D178 -> 0
A179: NET AMOUNT | E179: =SUM(E79:E178) -> 0 | F179: =SUM(F79:F178) -> 0 | G179: =SUM(G81:G178)+MAX(G79,G80) -> 0 | I179: =SUM(I81:I178)+IF(G71="Yes",I79,I80) -> 0 | J179: =SUM(J81:J178)+IF(G71="Yes",J79,J80) -> 0
A180: TOTAL AMOUNT INCLUSIVE OF PAINT MATERIAL | I180: =I179 -> 0
A181: TOTAL AMOUNT EXCLUSIVE OF PAINT MATERIAL | I181: =SUM(I81:I178) -> 0
...

Sheet 2022- Maruti Painting Dashboard
D1: Maruti Painting Schedule Utility
D2: ='Instruction Sheet'!C21 -> SAATH, Patna
F3: w.e.f. 22st June 2022
A4: City Category | C4: B | F4: Claim Details
A5: Dealer | C5: Alankar
A6: Model | C6: Celerio | F6: Insured Name | G6: ='Data Entry'!B5 -> Mr.
A7: Colour | C7: Metallic | F7: Policy No. | G7: ='Data Entry'!B4 -> 0
A8: Discount Mode | C8: System | F8: Claim No. | G8: ='Data Entry'!B3 -> 0
A9: No. of New Panels | C9: =COUNTIF(C12:C25,"New") -> 1 | F9: Vehicle No. | G9: ='Data Entry'!B18 -> 0
A10: No. of Old Panels | C10: =COUNTIF(C12:C25,"Old") -> 2 | F10: Surveyor's Name | G10: ='Data Entry'!B60 -> Dilip Kumar Sinha
A11: Side | B11: =B101 -> Name of Scheduled Panels | C11: =C101 -> Panel Type | D11: System Discount % | E11: Manual Discount % | F11: =H101 -> Scheduled Rate | G11: =I101 -> Discounted Rate | H11: =J101 -> Painting (Labour) | I11: =K101 -> Paint Material
A12: FR | B12: Front Bumper | C12: New | D12: =IF(OR($B12="",$C12=""),"",G102) -> 0 | E12: 0 | F12: =IF(OR(B12="",C12="",B12=0,C12=0),"",IF(OR(B12="Select",C12="Select",$C$6="Select"),"",VLOOKUP(IF(B12="Qr. Panel","Fender",B12),$B$45:$X$54,$C$88,FALSE))) -> 4029 | G12: =IF(OR($B12="",$C12=""),"",ROUND(F12*(100-IF($C$8="System",D12,E12))/100,0)) -> 4029 | H12: =IF(OR($B12="",$C12=""),"",ROUND(G12*0.75,0)) -> 3022 | I12: =IF(OR($B12="",$C12=""),"",G12-H12) -> 1007
A13: RH | B13: Fender | C13: Old | D13: =IF(OR($B13="",$C13=""),"",G103) -> 20 | E13: 30 | F13: =IF(OR(B13="",C13="",B13=0,C13=0),"",IF(OR(B13="Select",C13="Select",$C$6="Select"),"",VLOOKUP(IF(B13="Qr. Panel","Fender",B13),$B$45:$X$54,$C$88,FALSE))) -> 3258 | G13: =IF(OR($B13="",$C13=""),"",ROUND(F13*(100-IF($C$8="System",D13,E13))/100,0)) -> 2606 | H13: =IF(OR($B13="",$C13=""),"",ROUND(G13*0.75,0)) -> 1955 | I13: =IF(OR($B13="",$C13=""),"",G13-H13) -> 651
A14: RH | B14: Front Door | C14: Old | D14: =IF(OR($B14="",$C14=""),"",G104) -> 20 | E14: 30 | F14: =IF(OR(B14="",C14="",B14=0,C14=0),"",IF(OR(B14="Select",C14="Select",$C$6="Select"),"",VLOOKUP(IF(B14="Qr. Panel","Fender",B14),$B$45:$X$54,$C$88,FALSE))) -> 4408 | G14: =IF(OR($B14="",$C14=""),"",ROUND(F14*(100-IF($C$8="System",D14,E14))/100,0)) -> 3526 | H14: =IF(OR($B14="",$C14=""),"",ROUND(G14*0.75,0)) -> 2645 | I14: =IF(OR($B14="",$C14=""),"",G14-H14) -> 881
D15: =IF(OR($B15="",$C15=""),"",G105) | E15: 85 | F15: =IF(OR(B15="",C15="",B15=0,C15=0),"",IF(OR(B15="Select",C15="Select",$C$6="Select"),"",VLOOKUP(IF(B15="Qr. Panel","Fender",B15),$B$45:$X$54,$C$88,FALSE))) | G15: =IF(OR($B15="",$C15=""),"",ROUND(F15*(100-IF($C$8="System",D15,E15))/100,0)) | H15: =IF(OR($B15="",$C15=""),"",ROUND(G15*0.75,0)) | I15: =IF(OR($B15="",$C15=""),"",G15-H15)
D16: =IF(OR($B16="",$C16=""),"",G106) | F16: =IF(OR(B16="",C16="",B16=0,C16=0),"",IF(OR(B16="Select",C16="Select",$C$6="Select"),"",VLOOKUP(IF(B16="Qr. Panel","Fender",B16),$B$45:$X$54,$C$88,FALSE))) | G16: =IF(OR($B16="",$C16=""),"",ROUND(F16*(100-IF($C$8="System",D16,E16))/100,0)) | H16: =IF(OR($B16="",$C16=""),"",ROUND(G16*0.75,0)) | I16: =IF(OR($B16="",$C16=""),"",G16-H16)
D17: =IF(OR($B17="",$C17=""),"",G107) | F17: =IF(OR(B17="",C17="",B17=0,C17=0),"",IF(OR(B17="Select",C17="Select",$C$6="Select"),"",VLOOKUP(IF(B17="Qr. Panel","Fender",B17),$B$45:$X$54,$C$88,FALSE))) | G17: =IF(OR($B17="",$C17=""),"",ROUND(F17*(100-IF($C$8="System",D17,E17))/100,0)) | H17: =IF(OR($B17="",$C17=""),"",ROUND(G17*0.75,0)) | I17: =IF(OR($B17="",$C17=""),"",G17-H17)
D18: =IF(OR($B18="",$C18=""),"",G108) | F18: =IF(OR(B18="",C18="",B18=0,C18=0),"",IF(OR(B18="Select",C18="Select",$C$6="Select"),"",VLOOKUP(IF(B18="Qr. Panel","Fender",B18),$B$45:$X$54,$C$88,FALSE))) | G18: =IF(OR($B18="",$C18=""),"",ROUND(F18*(100-IF($C$8="System",D18,E18))/100,0)) | H18: =IF(OR($B18="",$C18=""),"",ROUND(G18*0.75,0)) | I18: =IF(OR($B18="",$C18=""),"",G18-H18)
D19: =IF(OR($B19="",$C19=""),"",G109) | F19: =IF(OR(B19="",C19="",B19=0,C19=0),"",IF(OR(B19="Select",C19="Select",$C$6="Select"),"",VLOOKUP(IF(B19="Qr. Panel","Fender",B19),$B$45:$X$54,$C$88,FALSE))) | G19: =IF(OR($B19="",$C19=""),"",ROUND(F19*(100-IF($C$8="System",D19,E19))/100,0)) | H19: =IF(OR($B19="",$C19=""),"",ROUND(G19*0.75,0)) | I19: =IF(OR($B19="",$C19=""),"",G19-H19)
D20: =IF(OR($B20="",$C20=""),"",G110) | F20: =IF(OR(B20="",C20="",B20=0,C20=0),"",IF(OR(B20="Select",C20="Select",$C$6="Select"),"",VLOOKUP(IF(B20="Qr. Panel","Fender",B20),$B$45:$X$54,$C$88,FALSE))) | G20: =IF(OR($B20="",$C20=""),"",ROUND(F20*(100-IF($C$8="System",D20,E20))/100,0)) | H20: =IF(OR($B20="",$C20=""),"",ROUND(G20*0.75,0)) | I20: =IF(OR($B20="",$C20=""),"",G20-H20)
D21: =IF(OR($B21="",$C21=""),"",G111) | F21: =IF(OR(B21="",C21="",B21=0,C21=0),"",IF(OR(B21="Select",C21="Select",$C$6="Select"),"",VLOOKUP(IF(B21="Qr. Panel","Fender",B21),$B$45:$X$54,$C$88,FALSE))) | G21: =IF(OR($B21="",$C21=""),"",ROUND(F21*(100-IF($C$8="System",D21,E21))/100,0)) | H21: =IF(OR($B21="",$C21=""),"",ROUND(G21*0.75,0)) | I21: =IF(OR($B21="",$C21=""),"",G21-H21)
D22: =IF(OR($B22="",$C22=""),"",G112) | F22: =IF(OR(B22="",C22="",B22=0,C22=0),"",IF(OR(B22="Select",C22="Select",$C$6="Select"),"",VLOOKUP(IF(B22="Qr. Panel","Fender",B22),$B$45:$X$54,$C$88,FALSE))) | G22: =IF(OR($B22="",$C22=""),"",ROUND(F22*(100-IF($C$8="System",D22,E22))/100,0)) | H22: =IF(OR($B22="",$C22=""),"",ROUND(G22*0.75,0)) | I22: =IF(OR($B22="",$C22=""),"",G22-H22)
D23: =IF(OR($B23="",$C23=""),"",G113) | F23: =IF(OR(B23="",C23="",B23=0,C23=0),"",IF(OR(B23="Select",C23="Select",$C$6="Select"),"",VLOOKUP(IF(B23="Qr. Panel","Fender",B23),$B$45:$X$54,$C$88,FALSE))) | G23: =IF(OR($B23="",$C23=""),"",ROUND(F23*(100-IF($C$8="System",D23,E23))/100,0)) | H23: =IF(OR($B23="",$C23=""),"",ROUND(G23*0.75,0)) | I23: =IF(OR($B23="",$C23=""),"",G23-H23)
D24: =IF(OR($B24="",$C24=""),"",G114) | F24: =IF(OR(B24="",C24="",B24=0,C24=0),"",IF(OR(B24="Select",C24="Select",$C$6="Select"),"",VLOOKUP(IF(B24="Qr. Panel","Fender",B24),$B$45:$X$54,$C$88,FALSE))) | G24: =IF(OR($B24="",$C24=""),"",ROUND(F24*(100-IF($C$8="System",D24,E24))/100,0)) | H24: =IF(OR($B24="",$C24=""),"",ROUND(G24*0.75,0)) | I24: =IF(OR($B24="",$C24=""),"",G24-H24)
D25: =IF(OR($B25="",$C25=""),"",G115) | F25: =IF(OR(B25="",C25="",B25=0,C25=0),"",IF(OR(B25="Select",C25="Select",$C$6="Select"),"",VLOOKUP(IF(B25="Qr. Panel","Fender",B25),$B$45:$X$54,$C$88,FALSE))) | G25: =IF(OR($B25="",$C25=""),"",ROUND(F25*(100-IF($C$8="System",D25,E25))/100,0)) | H25: =IF(OR($B25="",$C25=""),"",ROUND(G25*0.75,0)) | I25: =IF(OR($B25="",$C25=""),"",G25-H25)
A26: Side | B26: Other Panels | C26: Panel Name
B27: Others | G27: =IF(F27<>"",I117,"") | H27: =IF(F27<>"",J117,"") | I27: =IF(F27<>"",K117,"")
B28: Others | G28: =IF(F28<>"",I118,"") | H28: =IF(F28<>"",J118,"") | I28: =IF(F28<>"",K118,"")
B29: Others | G29: =IF(F29<>"",I119,"") | H29: =IF(F29<>"",J119,"") | I29: =IF(F29<>"",K119,"")
B30: Others | G30: =IF(F30<>"",I120,"") | H30: =IF(F30<>"",J120,"") | I30: =IF(F30<>"",K120,"")
B31: Others | G31: =IF(F31<>"",I121,"") | H31: =IF(F31<>"",J121,"") | I31: =IF(F31<>"",K121,"")
C32: Total | F32: =SUM(F12:F31) -> 11695 | G32: =SUM(G12:G31) -> 10161 | H32: =SUM(H12:H31) -> 7622 | I32: =SUM(I12:I31) -> 2539
B34: For Alankar | C34: Paint Material Rate (Per Unit) | G34: 45.65 | H34: =IF(G32=0,0,G32-I34) -> 7604.6 | I34: =IF(G32=0,0,G34*(INT(I32/G34)+1)) -> 2556.4
G40: Surveyor's Signature
B42: PAINTING SCHEDULE
B43: =VLOOKUP("Header"&I72,A125:AE278,2,FALSE)&" : "&C7 -> Panel wise Painting Charges -City Category "B" : Metallic
B44: Panels | C44: Alto-800 | D44: Alto-K10 | E44: Zen/Zen Estilo | F44: Ertiga | G44: New Wagon R | H44: A Star | I44: Ritz | J44: Swift | K44: Swift Dzire | L44: Versa/Eeco | M44: Vitara | N44: SX4 | O44: Big New Wagon R | P44: Ciaz | Q44: S-Cross | R44: Baleno (new) | S44: Celerio | T44: Vitara Brezza | U44: Ignis | V44: =+V152 -> New Ertiga | W44: Baleno (Old) | X44: Car-800 | Y44: Omni | AA44: Super Carry | AC44: Gypsy
B45: Front Bumper | C45: =VLOOKUP($I$72&$B45,$A$125:$AA$278,COLUMN(),FALSE) -> 3841 | D45: =VLOOKUP($I$72&$B45,$A$125:$AA$278,COLUMN(),FALSE) -> 4184 | E45: =VLOOKUP($I$72&$B45,$A$125:$AA$278,COLUMN(),FALSE) -> 4665 | F45: =VLOOKUP($I$72&$B45,$A$125:$AA$278,COLUMN(),FALSE) -> 4462 | G45: =VLOOKUP($I$72&$B45,$A$125:$AA$278,COLUMN(),FALSE) -> 4029 | H45: =VLOOKUP($I$72&$B45,$A$125:$AA$278,COLUMN(),FALSE) -> 4799 | I45: =VLOOKUP($I$72&$B45,$A$125:$AA$278,COLUMN(),FALSE) -> 4911 | J45: =VLOOKUP($I$72&$B45,$A$125:$AA$278,COLUMN(),FALSE) -> 4858 | ... X45: =VLOOKUP($I$72&$B45,$A$125:$AA$278,COLUMN(),FALSE) -> 0
B46: Rear Bumper | C46: =VLOOKUP($I$72&$B46,$A$125:$AA$278,COLUMN(),FALSE) -> 3841 | D46: =VLOOKUP($I$72&$B46,$A$125:$AA$278,COLUMN(),FALSE) -> 3970 | E46: =VLOOKUP($I$72&$B46,$A$125:$AA$278,COLUMN(),FALSE) -> 4109 | F46: =VLOOKUP($I$72&$B46,$A$125:$AA$278,COLUMN(),FALSE) -> 4820 | G46: =VLOOKUP($I$72&$B46,$A$125:$AA$278,COLUMN(),FALSE) -> 3906 | H46: =VLOOKUP($I$72&$B46,$A$125:$AA$278,COLUMN(),FALSE) -> 4328 | I46: =VLOOKUP($I$72&$B46,$A$125:$AA$278,COLUMN(),FALSE) -> 4473 | J46: =VLOOKUP($I$72&$B46,$A$125:$AA$278,COLUMN(),FALSE) -> 4858 | ... X46: =VLOOKUP($I$72&$B46,$A$125:$AA$278,COLUMN(),FALSE) -> 0
B47: Bonnet | C47: =VLOOKUP($I$72&$B47,$A$125:$AA$278,COLUMN(),FALSE) -> 4285 | D47: =VLOOKUP($I$72&$B47,$A$125:$AA$278,COLUMN(),FALSE) -> 4778 | E47: =VLOOKUP($I$72&$B47,$A$125:$AA$278,COLUMN(),FALSE) -> 4194 | F47: =VLOOKUP($I$72&$B47,$A$125:$AA$278,COLUMN(),FALSE) -> 4564 | G47: =VLOOKUP($I$72&$B47,$A$125:$AA$278,COLUMN(),FALSE) -> 4146 | H47: =VLOOKUP($I$72&$B47,$A$125:$AA$278,COLUMN(),FALSE) -> 3996 | I47: =VLOOKUP($I$72&$B47,$A$125:$AA$278,COLUMN(),FALSE) -> 4462 | J47: =VLOOKUP($I$72&$B47,$A$125:$AA$278,COLUMN(),FALSE) -> 4767 | ... X47: =VLOOKUP($I$72&$B47,$A$125:$AA$278,COLUMN(),FALSE) -> 3970
B48: Fender | C48: =VLOOKUP($I$72&$B48,$A$125:$AA$278,COLUMN(),FALSE) -> 3210 | D48: =VLOOKUP($I$72&$B48,$A$125:$AA$278,COLUMN(),FALSE) -> 3178 | E48: =VLOOKUP($I$72&$B48,$A$125:$AA$278,COLUMN(),FALSE) -> 3301 | F48: =VLOOKUP($I$72&$B48,$A$125:$AA$278,COLUMN(),FALSE) -> 3322 | G48: =VLOOKUP($I$72&$B48,$A$125:$AA$278,COLUMN(),FALSE) -> 3221 | H48: =VLOOKUP($I$72&$B48,$A$125:$AA$278,COLUMN(),FALSE) -> 3210 | I48: =VLOOKUP($I$72&$B48,$A$125:$AA$278,COLUMN(),FALSE) -> 3167 | J48: =VLOOKUP($I$72&$B48,$A$125:$AA$278,COLUMN(),FALSE) -> 3371 | ... X48: =VLOOKUP($I$72&$B48,$A$125:$AA$278,COLUMN(),FALSE) -> 3146
B49: Front Door | C49: =VLOOKUP($I$72&$B49,$A$125:$AA$278,COLUMN(),FALSE) -> 4205 | D49: =VLOOKUP($I$72&$B49,$A$125:$AA$278,COLUMN(),FALSE) -> 4205 | E49: =VLOOKUP($I$72&$B49,$A$125:$AA$278,COLUMN(),FALSE) -> 4205 | F49: =VLOOKUP($I$72&$B49,$A$125:$AA$278,COLUMN(),FALSE) -> 4542 | G49: =VLOOKUP($I$72&$B49,$A$125:$AA$278,COLUMN(),FALSE) -> 4489 | H49: =VLOOKUP($I$72&$B49,$A$125:$AA$278,COLUMN(),FALSE) -> 4366 | I49: =VLOOKUP($I$72&$B49,$A$125:$AA$278,COLUMN(),FALSE) -> 4489 | J49: =VLOOKUP($I$72&$B49,$A$125:$AA$278,COLUMN(),FALSE) -> 4612 | ... X49: =VLOOKUP($I$72&$B49,$A$125:$AA$278,COLUMN(),FALSE) -> 4061
B50: Rear Door | C50: =VLOOKUP($I$72&$B50,$A$125:$AA$278,COLUMN(),FALSE) -> 4205 | D50: =VLOOKUP($I$72&$B50,$A$125:$AA$278,COLUMN(),FALSE) -> 4205 | E50: =VLOOKUP($I$72&$B50,$A$125:$AA$278,COLUMN(),FALSE) -> 4205 | F50: =VLOOKUP($I$72&$B50,$A$125:$AA$278,COLUMN(),FALSE) -> 4869 | G50: =VLOOKUP($I$72&$B50,$A$125:$AA$278,COLUMN(),FALSE) -> 4489 | H50: =VLOOKUP($I$72&$B50,$A$125:$AA$278,COLUMN(),FALSE) -> 4366 | I50: =VLOOKUP($I$72&$B50,$A$125:$AA$278,COLUMN(),FALSE) -> 4489 | J50: =VLOOKUP($I$72&$B50,$A$125:$AA$278,COLUMN(),FALSE) -> 4612 | ... X50: =VLOOKUP($I$72&$B50,$A$125:$AA$278,COLUMN(),FALSE) -> 4061
B51: Qr.Panel | C51: =C48 -> 3210 | D51: =D48 -> 3178 | E51: =E48 -> 3301 | F51: =F48 -> 3322 | G51: =G48 -> 3221 | H51: =H48 -> 3210 | I51: =I48 -> 3167 | J51: =J48 -> 3371 | ... X51: =X48 -> 3146
B52: Back Door | C52: =VLOOKUP($I$72&$B52,$A$125:$AA$278,COLUMN(),FALSE) -> 4185 | D52: =VLOOKUP($I$72&$B52,$A$125:$AA$278,COLUMN(),FALSE) -> 4184 | E52: =VLOOKUP($I$72&$B52,$A$125:$AA$278,COLUMN(),FALSE) -> 4184 | F52: =VLOOKUP($I$72&$B52,$A$125:$AA$278,COLUMN(),FALSE) -> 4922 | G52: =VLOOKUP($I$72&$B52,$A$125:$AA$278,COLUMN(),FALSE) -> 4564 | H52: =VLOOKUP($I$72&$B52,$A$125:$AA$278,COLUMN(),FALSE) -> 3547 | I52: =VLOOKUP($I$72&$B52,$A$125:$AA$278,COLUMN(),FALSE) -> 4564 | J52: =VLOOKUP($I$72&$B52,$A$125:$AA$278,COLUMN(),FALSE) -> 4205 | ... X52: =VLOOKUP($I$72&$B52,$A$125:$AA$278,COLUMN(),FALSE) -> 3948
B53: Roof | C53: =VLOOKUP($I$72&$B53,$A$125:$AA$278,COLUMN(),FALSE) -> 6345 | D53: =VLOOKUP($I$72&$B53,$A$125:$AA$278,COLUMN(),FALSE) -> 6345 | E53: =VLOOKUP($I$72&$B53,$A$125:$AA$278,COLUMN(),FALSE) -> 6522 | F53: =VLOOKUP($I$72&$B53,$A$125:$AA$278,COLUMN(),FALSE) -> 9159 | G53: =VLOOKUP($I$72&$B53,$A$125:$AA$278,COLUMN(),FALSE) -> 7404 | H53: =VLOOKUP($I$72&$B53,$A$125:$AA$278,COLUMN(),FALSE) -> 6655 | I53: =VLOOKUP($I$72&$B53,$A$125:$AA$278,COLUMN(),FALSE) -> 7003 | J53: =VLOOKUP($I$72&$B53,$A$125:$AA$278,COLUMN(),FALSE) -> 6522 | ... X53: =VLOOKUP($I$72&$B53,$A$125:$AA$278,COLUMN(),FALSE) -> 6062
B54: Full Car Painting | C54: =VLOOKUP($I$72&$B54,$A$125:$AA$278,COLUMN(),FALSE) -> 40612 | D54: =VLOOKUP($I$72&$B54,$A$125:$AA$278,COLUMN(),FALSE) -> 41318 | E54: =VLOOKUP($I$72&$B54,$A$125:$AA$278,COLUMN(),FALSE) -> 41618 | F54: =VLOOKUP($I$72&$B54,$A$125:$AA$278,COLUMN(),FALSE) -> 46796 | G54: =VLOOKUP($I$72&$B54,$A$125:$AA$278,COLUMN(),FALSE) -> 42725 | H54: =VLOOKUP($I$72&$B54,$A$125:$AA$278,COLUMN(),FALSE) -> 41789 | I54: =VLOOKUP($I$72&$B54,$A$125:$AA$278,COLUMN(),FALSE) -> 43677 | J54: =VLOOKUP($I$72&$B54,$A$125:$AA$278,COLUMN(),FALSE) -> 44539 | ... X54: =VLOOKUP($I$72&$B54,$A$125:$AA$278,COLUMN(),FALSE) -> 33347
C56: Model | D56: Column No. | F56: Non Metalic Rate | H56: Paint Type | I56: %
B57: Select | C57: Alto-800 | D57: 2 | F57: 0.8 | H57: Metallic | I57: 1 | K57: Select
B58: Front Bumper | C58: Alto-K10 | D58: 3 | F58: 0.8 | H58: Non Metallic | I58: =VLOOKUP(C6,C57:F78,3,FALSE) -> 0 | K58: New
B59: Rear Bumper | C59: Zen/Zen Estilo | D59: 4 | F59: 0.8 | H59: PMW | I59: 1.11 | K59: Old
B60: Bonnet | C60: Ertiga | D60: 5 | F60: 0.8 | K60: Minor/Touch up
B61: Fender | C61: New Wagon R | D61: 6 | F61: 0.8
B62: Front Door | C62: A Star | D62: 7 | F62: 0.8 | H62: Select | I62: 2
B63: Rear Door | C63: Ritz | D63: 8 | F63: 0.8 | H63: Alankar | I63: 3
B64: Qr.Panel | C64: Swift | D64: 9 | F64: 0.8 | H64: Karlo | I64: 4
B65: Back Door | C65: Swift Dzire | D65: 10 | F65: 0.8 | H65: Vaus | I65: 5
B66: Roof | C66: Versa/Eeco | D66: 11 | F66: 0.8 | H66: City Auto | I66: 6
B67: Full Car Painting | C67: Vitara | D67: 12 | F67: 0.8 | H67: Good Wrench | I67: 7
C68: SX4 | D68: 13 | F68: 0.8 | H68: Tirupati | I68: 8
C69: =+O152 -> Big New Wagon R | D69: 14 | F69: 0.8 | H69: Reeshav | I69: 9
C70: Ciaz | D70: 15 | F70: 0.8 | H70: Others | I70: 10
C71: S-Cross | D71: 16 | F71: 0.8
C72: Baleno (new) | D72: 17 | F72: 0.8 | H72: City/Paint Code | I72: =IF(C7="Metallic","M"&C4,IF(C7="Non Metallic","NM"&C4,"PW"&C4)) -> MB
C73: Celerio | D73: 18 | F73: 0.8
C74: Vitara Brezza | D74: 19 | F74: 0.8
C75: Ignis | D75: 20 | F75: 0.8
C76: New Ertiga | D76: 21 | F76: 0.8
C77: Baleno (Old) | D77: 22 | F77: 0.8
C78: Car-800 | D78: 23 | F78: 0.8
B80: Workshop's Name | C80: =C5 -> Alankar
B81: Workshop Column | C81: =VLOOKUP(C80,H62:I70,2,FALSE) -> 3
B82: Colour | C82: =C7 -> Metallic
B83: Zero Depr | C83: =C8 -> System
B84: No. of New Panels | C84: =C9 -> 1
B85: No. of Old Panels | C85: =C10 -> 2
B86: Paint Material | C86: 25
B87: Painting | C87: 75
B88: Model Code | C88: =VLOOKUP(C6,C57:D78,2,FALSE) -> 18
B89: Painting % (M/NM/PMW) | C89: =VLOOKUP(C7,H57:I59,2,FALSE) -> 1
N90: Alankar | R90: All | U90: City Auto
B91: Panels | C91: Discounts | D91: Search Column | F91: Alankar | G91: Karlo | H91: Vaus | I91: City Auto | J91: Good Wrench | K91: Tirupati | L91: Reeshav | M91: Others | N91: No.Of Old Panel | O91: Discount | P91: Discount | R91: No. of New Panels | S91: Discount | U91: No.Of Old Panel | V91: Discount
B92: All | C92: Minor/Touch up | D92: =B92&C92 -> AllMinor/Touch up | F92: 35 | G92: 30 | H92: 20 | I92: 30 | J92: 30 | K92: 40 | L92: 30 | M92: 45 | N92: 0 | O92: 0 | P92: 0 | R92: 0 | S92: 0 | U92: 0 | V92: 0
B93: All | C93: Old | D93: =B93&C93 -> AllOld | F93: =VLOOKUP(C85,N92:P95,2,TRUE) -> 20 | G93: 30 | H93: 20 | I93: 30 | J93: 30 | K93: 30 | L93: 30 | M93: 45 | N93: 1 | O93: 10 | P93: 10 | R93: 1 | S93: 0 | U93: 1 | V93: 25
B94: All | C94: New | D94: =B94&C94 -> AllNew | F94: =VLOOKUP(C84,R92:S99,2,TRUE) -> 0 | G94: =VLOOKUP(C84,R92:S99,2,TRUE) -> 0 | H94: =VLOOKUP(C84,R92:S99,2,TRUE) -> 0 | I94: 30 | J94: 30 | K94: 20 | L94: =VLOOKUP(C84,R92:S99,2,TRUE) -> 0 | M94: 45 | N94: 2 | O94: 20 | P94: 20 | R94: 2 | S94: 8 | U94: 4 | V94: 25
B95: Bumper | C95: Minor/Touch up | D95: =B95&C95 -> BumperMinor/Touch up | F95: 30 | G95: 30 | H95: 20 | I95: 35 | J95: 30 | K95: 40 | L95: 30 | M95: 45 | N95: 3 | O95: 25 | P95: 25 | R95: 3 | S95: 10
B96: Bumper | C96: New | D96: =B96&C96 -> BumperNew | F96: =VLOOKUP(C84,R92:S99,2,TRUE) -> 0 | G96: =VLOOKUP(C84,R92:S99,2,TRUE) -> 0 | H96: =VLOOKUP(C84,R92:S99,2,TRUE) -> 0 | I96: 30 | J96: 30 | K96: 20 | L96: =VLOOKUP(C84,R92:S99,2,TRUE) -> 0 | M96: 45 | R96: 4 | S96: 12
B97: Bumper | C97: Old | D97: =B97&C97 -> BumperOld | F97: 30 | G97: 30 | H97: 20 | I97: 30 | J97: 30 | K97: 30 | L97: 30 | M97: 45 | R97: 5 | S97: 18
R98: 6 | S98: 20
R99: 7 | S99: 22
B100: CALCULATION
B101: Name of Scheduled Panels | C101: Panel Type | D101: Bumper (Y/N) | F101: Discount Code | G101: Discount % | H101: Scheduled Rate | I101: Discounted Rate | J101: Painting (Labour) | K101: Paint Material
B102: =B12 -> Front Bumper | C102: =C12 -> New | D102: =IF(RIGHT(B102,6)="Bumper",RIGHT(B102,6),"All") -> Bumper | F102: =D102&C102 -> BumperNew | G102: =IF(OR(C102=0,C102="Select"),0,IF(F102="AllSelect",0,VLOOKUP(D102&C102,$D$92:$M$97,$C$81,FALSE))) -> 0 | H102: =IF(F12<>"",F12,0) -> 4029 | I102: =ROUND(H102*(100-G102)/100,0) -> 4029 | J102: =IF($C$83="Yes",I102,ROUND(I102*0.75,0)) -> 3022 | K102: =IF($C$83="Yes",0,ROUND(I102*0.25,0)) -> 1007
B103: =B13 -> Fender | C103: =C13 -> Old | D103: =IF(RIGHT(B103,6)="Bumper",RIGHT(B103,6),"All") -> All | F103: =D103&C103 -> AllOld | G103: =IF(OR(C103=0,C103="Select"),0,IF(F103="AllSelect",0,VLOOKUP(D103&C103,$D$92:$M$97,$C$81,FALSE))) -> 20 | H103: =IF(F13<>"",F13,0) -> 3258 | I103: =ROUND(H103*(100-G103)/100,0) -> 2606 | J103: =IF($C$83="Yes",I103,ROUND(I103*0.75,0)) -> 1955 | K103: =IF($C$83="Yes",0,ROUND(I103*0.25,0)) -> 652
B104: =B14 -> Front Door | C104: =C14 -> Old | D104: =IF(RIGHT(B104,6)="Bumper",RIGHT(B104,6),"All") -> All | F104: =D104&C104 -> AllOld | G104: =IF(OR(C104=0,C104="Select"),0,IF(F104="AllSelect",0,VLOOKUP(D104&C104,$D$92:$M$97,$C$81,FALSE))) -> 20 | H104: =IF(F14<>"",F14,0) -> 4408 | I104: =ROUND(H104*(100-G104)/100,0) -> 3526 | J104: =IF($C$83="Yes",I104,ROUND(I104*0.75,0)) -> 2645 | K104: =IF($C$83="Yes",0,ROUND(I104*0.25,0)) -> 882
B105: =B15 -> 0 | C105: =C15 -> 0 | D105: =IF(RIGHT(B105,6)="Bumper",RIGHT(B105,6),"All") -> All | F105: =D105&C105 -> All0 | G105: =IF(OR(C105=0,C105="Select"),0,IF(F105="AllSelect",0,VLOOKUP(D105&C105,$D$92:$M$97,$C$81,FALSE))) -> 0 | H105: =IF(F15<>"",F15,0) -> 0 | I105: =ROUND(H105*(100-G105)/100,0) -> 0 | J105: =IF($C$83="Yes",I105,ROUND(I105*0.75,0)) -> 0 | K105: =IF($C$83="Yes",0,ROUND(I105*0.25,0)) -> 0
B106: =B16 -> 0 | C106: =C16 -> 0 | D106: =IF(RIGHT(B106,6)="Bumper",RIGHT(B106,6),"All") -> All | F106: =D106&C106 -> All0 | G106: =IF(OR(C106=0,C106="Select"),0,IF(F106="AllSelect",0,VLOOKUP(D106&C106,$D$92:$M$97,$C$81,FALSE))) -> 0 | H106: =IF(F16<>"",F16,0) -> 0 | I106: =ROUND(H106*(100-G106)/100,0) -> 0 | J106: =IF($C$83="Yes",I106,ROUND(I106*0.75,0)) -> 0 | K106: =IF($C$83="Yes",0,ROUND(I106*0.25,0)) -> 0
B107: =B17 -> 0 | C107: =C17 -> 0 | D107: =IF(RIGHT(B107,6)="Bumper",RIGHT(B107,6),"All") -> All | F107: =D107&C107 -> All0 | G107: =IF(OR(C107=0,C107="Select"),0,IF(F107="AllSelect",0,VLOOKUP(D107&C107,$D$92:$M$97,$C$81,FALSE))) -> 0 | H107: =IF(F17<>"",F17,0) -> 0 | I107: =ROUND(H107*(100-G107)/100,0) -> 0 | J107: =IF($C$83="Yes",I107,ROUND(I107*0.75,0)) -> 0 | K107: =IF($C$83="Yes",0,ROUND(I107*0.25,0)) -> 0
B108: =B18 -> 0 | C108: =C18 -> 0 | D108: =IF(RIGHT(B108,6)="Bumper",RIGHT(B108,6),"All") -> All | F108: =D108&C108 -> All0 | G108: =IF(OR(C108=0,C108="Select"),0,IF(F108="AllSelect",0,VLOOKUP(D108&C108,$D$92:$M$97,$C$81,FALSE))) -> 0 | H108: =IF(F18<>"",F18,0) -> 0 | I108: =ROUND(H108*(100-G108)/100,0) -> 0 | J108: =IF($C$83="Yes",I108,ROUND(I108*0.75,0)) -> 0 | K108: =IF($C$83="Yes",0,ROUND(I108*0.25,0)) -> 0
B109: =B19 -> 0 | C109: =C19 -> 0 | D109: =IF(RIGHT(B109,6)="Bumper",RIGHT(B109,6),"All") -> All | F109: =D109&C109 -> All0 | G109: =IF(OR(C109=0,C109="Select"),0,IF(F109="AllSelect",0,VLOOKUP(D109&C109,$D$92:$M$97,$C$81,FALSE))) -> 0 | H109: =IF(F19<>"",F19,0) -> 0 | I109: =ROUND(H109*(100-G109)/100,0) -> 0 | J109: =IF($C$83="Yes",I109,ROUND(I109*0.75,0)) -> 0 | K109: =IF($C$83="Yes",0,ROUND(I109*0.25,0)) -> 0
...

Sheet Re-inspection Report
A1: ='Data Entry'!$B$60 -> Dilip Kumar Sinha | E1: ='Data Entry'!$B$61 -> V/477, Vidyapuri, Kankarbagh, Patna-800020
A2: SURVEYOR/LOSS ASSESSOR/VALUER | E2: Mobile Number | F2: ='Data Entry'!$B$63 -> 9334110636
A3: License Number | C3: ='Data Entry'!$B$66 -> 63315 | E3: Date of Expiry | F3: ='Data Entry'!$B$67 -> 46469
A4: Email Id | C4: ='Data Entry'!$B$65 -> dilipsinha11k@gmail.com | E4: Telephone Number | F4: ='Data Entry'!$B$64 -> 0
A5: PRIVATE AND CONFIDENTIAL MOTOR (REINSPECTION) SURVEY REPORT
A7: INSURER | C7: NATIONAL INSURANCE COMPANY LTD. | E7: POLICY NO. | F7: ='Data Entry'!$B$4 -> 0
A8: INSURED | C8: ='Data Entry'!$B$5 -> Mr. | E8: ='Data Entry'!$A$3 -> CLAIM NUMBER | F8: ='Data Entry'!$B$3 -> 0
A9: PERIOD OF INSURANCE | C9: ='Data Entry'!$B$10 -> 0 | D9: ='Data Entry'!$D$10 -> 0 | E9: VEHICLE NO. | F9: ='Data Entry'!$B$18 -> 0
H10: Developed by SAATH, Patna.
A11: The aforesaid insured's vehicle number | D11: =$F$9 -> 0 | E11: was Re-inspected on | F11: ='Data Entry'!$B$51 -> 0
A12: after being intimated by the Repairer. I have inspected the vehicle minutely and found that the repairings
A13: seemly and satisfactorily. All the mechanical & electrical/electronics systems/units are working properly
A14: and the vehicle was in Roadworthy condition. During Survey I noticed that the following parts/panels are
A15: replaced as per our recommendation:
A17: Sl No | B17: Name of Parts | C17: Reason For Replacement Comment/Estimated Cost | D17: Photo of Damaged Parts | E17: Photo of Replaced Parts | F17: Photo Identification
A18: 1 | B18: =IF('Assessment Sheet'!B81<>"",'Assessment Sheet'!B81,"") | C18: =IF('Assessment Sheet'!F81<>"",'Assessment Sheet'!F81,"") | D18: Yes | E18: Yes | F18: Yes
A19: 2 | B19: =IF('Assessment Sheet'!B82<>"",'Assessment Sheet'!B82,"") | C19: =IF('Assessment Sheet'!F82<>"",'Assessment Sheet'!F82,"")
A20: 3 | B20: =IF('Assessment Sheet'!B83<>"",'Assessment Sheet'!B83,"") | C20: =IF('Assessment Sheet'!F83<>"",'Assessment Sheet'!F83,"")
A21: 4 | B21: =IF('Assessment Sheet'!B84<>"",'Assessment Sheet'!B84,"") | C21: =IF('Assessment Sheet'!F84<>"",'Assessment Sheet'!F84,"")
A22: 5 | B22: =IF('Assessment Sheet'!B85<>"",'Assessment Sheet'!B85,"") | C22: =IF('Assessment Sheet'!F85<>"",'Assessment Sheet'!F85,"")
A23: 6 | B23: =IF('Assessment Sheet'!B86<>"",'Assessment Sheet'!B86,"") | C23: =IF('Assessment Sheet'!F86<>"",'Assessment Sheet'!F86,"")
A24: 7 | B24: =IF('Assessment Sheet'!B87<>"",'Assessment Sheet'!B87,"") | C24: =IF('Assessment Sheet'!F87<>"",'Assessment Sheet'!F87,"")
A25: 8 | B25: =IF('Assessment Sheet'!B88<>"",'Assessment Sheet'!B88,"") | C25: =IF('Assessment Sheet'!F88<>"",'Assessment Sheet'!F88,"")
A26: 9 | B26: =IF('Assessment Sheet'!B89<>"",'Assessment Sheet'!B89,"") | C26: =IF('Assessment Sheet'!F89<>"",'Assessment Sheet'!F89,"")
A27: 10 | B27: =IF('Assessment Sheet'!B90<>"",'Assessment Sheet'!B90,"") | C27: =IF('Assessment Sheet'!F90<>"",'Assessment Sheet'!F90,"")
A28: 11 | B28: =IF('Assessment Sheet'!B91<>"",'Assessment Sheet'!B91,"") | C28: =IF('Assessment Sheet'!F91<>"",'Assessment Sheet'!F91,"")
A29: 12 | B29: =IF('Assessment Sheet'!B92<>"",'Assessment Sheet'!B92,"") | C29: =IF('Assessment Sheet'!F92<>"",'Assessment Sheet'!F92,"")
A30: 13 | B30: =IF('Assessment Sheet'!B93<>"",'Assessment Sheet'!B93,"") | C30: =IF('Assessment Sheet'!F93<>"",'Assessment Sheet'!F93,"")
... A115: 98 | B115: =IF('Assessment Sheet'!B178<>"",'Assessment Sheet'!B178,"") | C115: =IF('Assessment Sheet'!F178<>"",'Assessment Sheet'!F178,"")
A117: Comments(If any):
A118: NO
A120: This concludes my report which is being issued without prejudice, subject to the terms and conditions of the Insurance policy and final approval of the insurer.
B122: Thanking You,
F123: Yours faithfully,
E125: ='Data Entry'!$B$60 -> Dilip Kumar Sinha
F126: Surveyor
C131: Submitted to National Insurance Company Limited

Sheet Surveyor's Master
A1: SL | B1: Surveyor's Name | C1: Address Line | D1: Mobile Number | E1: Telephone Number | F1: Email Id | G1: License Number | H1: GSTIN | I1: Date of Expiry | J1: Bank Name | K1: Bank Addess | L1: IFSC Code | M1: Account Number | N1: PAN Detail | O1: Easy Code
A2: 1 | B2: Abhay Kumar | C2: Professors' Colony, House no.- NY / 110, Janta Road, New Yarpur, Patna - 800001 | D2: 9835240141 | F2: abhay1284.2008@rediffmail.com | G2: 43409 | H2: 10AGXPK2675G1Z8 | I2: 43344 | J2: State Bank of India | K2: Boring Rd | L2: SBIN0001435 | M2: 10749091506 | N2: AGXPK2675G
A3: 2 | B3: Amar Kant Jha | C3: 37,Mithila Colony, Road No-5, Near Baba Chowk, Patel Nagar(North) Patna-800024 | D3: 9334784485 | E3: 6122284485 | F3: amarkantjha@yahoo.com | G3: 6597 | H3: Not Appiled | I3: 43116 | J3: Indian Bank | K3: West Gandhi Maidan | L3: IDIB000P027 | M3: 537708116 | N3: ABOPJ5205B
A4: 3 | B4: Anuj Kumar | C4: B/4, Flat No.404, PRDA Apartment, South S K Puri, Patna-800001 | D4: 9835093602 | E4: 9431040529 | F4: anujkumar2259@gmail.com | G4: 36915 | H4: 10ABXPK3831D1ZW | I4: 42859 | J4: State Bank of India | K4: SPBB Patna | L4: SBIN0004070 | M4: 10498107511 | N4: ABXPK3831D
A5: 4 | B5: Arun Kumar Singh | C5: 303, Gauri Shankar Apartment (Phase-I),Kurji, Patna-800010 | D5: 9835461746 | E5: 9905246796 | F5: arunkumar.kurji@gmail.com | G5: 37267, Easi Code-95305303 | H5: 10ANZPS2969J2Z6 | I5: 45128 | J5: Uco Bank | K5: Mahalekhakar Bhawan | L5: UCBA0002050 | M5: 20500100000820 | N5: ANZPS2969J | O5: 95305303
A6: 5 | B6: Ashutosh Kumar | C6: Swastic Campus, Lane No: 3, Chandmari Road, Patna-800020 | D6: 9835089586 | F6: ashutosh_swastic@yahoo.co.in | G6: 33583 | H6: Not Appiled | I6: 42609
A7: 6 | B7: Babu Lal Prasad | C7: Bank of India Colony, Raja Bazar, Patna | D7: 9835289661 | E7: 0612-2582389 | F7: babulalprasad44@gmail.com | G7: 47276 | H7: Not Appiled | I7: 43623 | J7: State Bank of India | K7: Raja Bazar | L7: SBIN0003563 | M7: 10076879792 | N7: AGTPP9531A
A8: 7 | B8: Balbir Singh | C8: Near Loyola School, Kurji, Patna | D8: 9835097356 | E8: 9431647242 | F8: erbalbir56@gmail.com | G8: 52734 | H8: Not Appiled | I8: 44116 | J8: State Bank of India | K8: Dak Bunglow Road | L8: SBIN0007506 | M8: 10633807192 | N8: AGNPS6095G
A9: 8 | B9: Binay Kumar | C9: 607, "B", Block , Gagan Appartment, Exhibition Road, Patna-800001 | D9: 9334536429 | E9: 8084768283 | F9: binayfast@gmail.com | G9: 47434 | H9: Not Appiled | I9: 43637 | J9: Union Bank | K9: Raja Bazar | L9: UBIN545325 | M9: 453202010004415 | N9: BDOPK2556F
A10: 9 | B10: Chandra Churamani Upadhyay | C10: West Patel Nagar, Professors Colony, Patna-800023 | D10: 09431020343/7543033389 | E10: 0612-2292353 | F10: ccm_upadhyay_1961@yahoo.co.in/ccmupadhyay@gmail.com | G10: 36013 | H10: Not Appiled | I10: 42791 | J10: State Bank of India | K10: IGIMS, Patna | L10: SBIN 0007945 | M10: 10119455281 | N10: AAGPU7483D
A11: 10 | B11: Dilip Kumar Sinha | C11: V/477, Vidyapuri, Kankarbagh, Patna-800020 | D11: 9334110636 | F11: dilipsinha11k@gmail.com | G11: 63315 | H11: Not Appiled | I11: 43182 | J11: State Bank of India | K11: Hanuman Nagar Br. | L11: SBIN0009005 | M11: 20019295926 | N11: APZPS2395Q
A12: 11 | B12: Krishna Kumar Singh | C12: Patna | D12: 9431624101 | F12: kksinghsurveyor.singh@gmail.com | G12: 57716 | H12: Not Appiled | I12: 42747 | J12: HDFC Bank Ltd. | K12: Exhibition Road | L12: HDFC0000186 | M12: 01861070036004 | N12: ATAPS1143F
A13: 12 | B13: Kundan Karmvir | C13: At:-Shivpuri,Panchmandir Lane,Shivpuri Patna-800023 | D13: 9334605082 | F13: kundankarmvir@gmail.com | G13: 72838 | H13: Not Appiled | I13: 43699 | J13: State Bank of India | K13: Patliputra Colony | L13: SBIN0001513 | M13: 10636281133 | N13: AONPK5766L
A14: 13 | B14: Manoj Kumar | C14: Post Office (End), Punaichak, Patna - 800023 | D14: 9835422098 | G14: 67483 | H14: Not Appiled | I14: 43486 | J14: State Bank of India | K14: SPB Branch, Patna | L14: SBIN0004070 | M14: 10497963391 | N14: AJDPK9426C
A15: 14 | B15: Mukesh Kumar | C15: Sarmera Kothi, Road No.1, Rajendra Nagar, Patna-800016 | D15: 9835422098 | G15: 67483 | H15: Not Appiled | I15: 43486 | J15: State Bank of India | K15: Patna | L15: SBIN0004070 | M15: 10497963391 | N15: AJDPK9426C
A16: 15 | B16: Prakash Narayan | C16: New Patliputra Colony, Patna | D16: 9334660344 | F16: prakash.narayan33@gmail.com | G16: 74881 | H16: Not Appiled | I16: 43095 | J16: Punjab Bank of India | K16: Boring Rd
A17: 16 | B17: Prem Kumar Sharma | C17: H/O Dip Narayan Singh -Opp SBI , Behind ,M/S Patliputra Enterprises ,Kankarbagh , Patna-800020 | D17: 9934085231 | E17: 9523059657 | F17: sharmapremkumar49@gmail.com | G17: 70113 | H17: Not Appiled | I17: 43593 | J17: PNB | K17: Kankarbagh Branch | L17: PUNB0149900 | M17: 1.4990001e+15 | N17: AQFPS1525B
A18: 17 | B18: Raj Kumar | C18: 311, Ratnagiri Apartment, Rajabazar, Patna-800014 | D18: 9430921513 | F18: raj081963@gmail.com | G18: 27485 | H18: 10AFDPK5100P1ZT | I18: 43918 | J18: State Bank of India | K18: New Dak Bunglow Rd | L18: SBIN0003476 | M18: 10151360658 | N18: AFDPK5100P
A19: 18 | B19: Rajesh Kumar Jha | C19: 409, Sheela Residecy, Vishnudev Marg, East Boring Canal Road, Patna-800001 | D19: 9709608580 | F19: rajeshjha933@gmail.com | G19: 58085 | H19: Not Appiled | I19: 42777 | J19: State Bank of India | K19: Patliputra Colony | L19: SBIN0001513 | M19: 10636237274 | N19: ADGPJ8664C
A20: 19 | B20: Rajiv Kumar | C20: Manishakuntalam Kunj, L.B.Shastri Path, Anishabad, Patna-800002 | D20: 9431009640 | F20: manishakuntalam@yahoo.co.in | G20: 43258 | H20: Not Appiled | I20: 43338 | J20: Canara Bank | K20: Anishabad | L20: CNRB0002819 | M20: 2819101002092 | N20: AEKPK1124P
A21: 20 | B21: Ravi Ranjan Prasad | C21: PAtna | D21: 9835409936 | E21: 9471027900 | F21: rrp9936@gmail.com | G21: 37165 | H21: Not Appiled | I21: 42907 | J21: Canara Bank | K21: Exhibiton Rd. | L21: CNRB0002004 | M21: 2004101007959 | N21: AKJPP7098H
A22: 21 | B22: Sanjay K Singh (II) | C22: R-11, Jagat Vihar Colony, Ashiana Nagar, Patna-800025 | D22: 9835439174 | E22: 9546109332 | F22: sanjaysingh.surveyor@gmail.com | G22: 72510 | H22: Not Appiled | I22: 43303 | J22: State Bank of India | K22: Ashiana Nagar | L22: SBIN0009004 | M22: 010238640005 | N22: AHRPS6966R
A23: 22 | B23: Sanjay Kumar Singh | C23: C/O Vijayeshwar Pd. Road No. 1, Kankarbagh, Patna 800020 | D23: 9334847220 | E23: NA | F23: singh.sanjay67@gmail.com | G23: 51068 | H23: Not Appiled | I23: 43946 | J23: HDFC Bank Ltd | K23: Kankarbagh Branch | L23: HDFC0000477 | M23: 04772000006399 | N23: ANNPS5129G
A24: 23 | B24: Satish Kumar | C24: Ramjaipal Nagar, Gola Road, Danapur, Patna - 801503 | D24: 9835015327 | E24: 9304768851 | F24: satishkrcomp@rediffmail.com | G24: 26403 | H24: Not Appiled | I24: 43813 | J24: Union )Bank Of India | K24: Patna - Raja Bazar | L24: UBIN0545325 | M24: 453202010005804 | N24: AGOPK2068E
A25: 24 | B25: Shailesh Kumar | C25: V' Niwas, Lane-1, Salimpur Ahra, Kadam kuan, Patna-800003 | D25: 9835024275 | E25: 9939088499 | F25: shailesh64@in.com | G25: 25736 | H25: Not Appiled | I25: 43760 | J25: State Bank of India | K25: Kankarbagh Branch | L25: SBIN0004445 | M25: 30297480856 | N25: AGLPK0913D
A26: 25 | B26: Shankar Prasad Singh | C26: Ground Floor, Satyawati Complex, Kankarbagh Main Road, Patna-800020 | D26: 9431017033 | F26: spsinghsurveyor@yahoo.com | G26: 31805 | H26: Not Appiled | I26: 43555 | J26: IDBI Bank | L26: IBKL0000065 | M26: 065104000102599 | N26: AJKPS5682F
A27: 26 | B27: Someshwar Kumar | C27: H/O Manager Roy, Prof Colony, Punai Chak, Patna-800023 | D27: 9431093209 | E27: 9835015428 | F27: someshwar_08@rediffmail.com | G27: 37151 | H27: Not Appiled | I27: 42914 | J27: Punjab Bank of India | K27: Punaichak, Patna | L27: PUNB0296800 | M27: 2968000100026750 | N27: AGJPK0198A
A28: 27 | B28: Sunil Kumar | C28: 205, Deo Sidhi Plaza, Near Colony More, Main Road Kankarbagh, Patna-800020 | D28: 9835262161 | E28: 9801640402 | F28: sk.nandn@gmail.com | G28: 63836 | H28: Not Appiled | I28: 43220 | J28: IDBI Bank | K28: Kankarbagh Branch | L28: IBKL0001020 | M28: 65104000045827 | N28: AHJPK0190K
A29: 28 | B29: Upendra Narayan Singh | C29: B- 65, Biscomaun Colony, Patna- 800 007 | D29: 9431860149 | E29: 2361422 | F29: unsingh.patna@gmail.com | G29: 27819 | H29: Not Appiled | I29: 43453 | J29: OBC | K29: Exhibition Road, Patna | L29: ORBC0100231 | M29: 02312010010260 | N29: AVNPS8480N
A30: 28 | B30: Others | C30: Please fill your data in the Surveyor Master Sheet | H30: Not Appiled
